[
  {
    "id": 171,
    "sku": "DCWO500",
    "name": "Danfels Coconut Water 500ml",
    "description": "",
    "storageLocation": "",
    "category": "Coconut Water",
    "metro": 40.8,
    "wholesale": 0.0,
    "price": 23.0,
    "cartonQty": 24,
    "weight": 0.0,
    "initialSupplier": "Vinut",
    "sellByUnit": true,
    "sellByCarton": true,
    "regional": 40.8,
    "archive": false,
    "image": "assets/images/Danfels_Coconut_Water_500ml.png"
  },
  {
    "id": 172,
    "sku": "DAVMIX500",
    "name": "Danfels Mixed 500ml",
    "description": "",
    "storageLocation": "",
    "category": "Aloe Vera",
    "metro": 40.8,
    "wholesale": 0.0,
    "price": 23.0,
    "cartonQty": 24,
    "weight": 0.0,
    "initialSupplier": "Vinut",
    "sellByUnit": true,
    "sellByCarton": true,
    "regional": 40.8,
    "archive": false,
    "image": "assets/images/Danfels_Mixed_500ml.png"
  },
  {
    "id": 181,
    "sku": "NOJ450",
    "name": "Nippys Orange Juice 450ml",
    "description": "",
    "storageLocation": "",
    "category": "Fruit Juice",
    "metro": 30.0,
    "wholesale": 0.0,
    "price": 23.91,
    "cartonQty": 12,
    "weight": 0.0,
    "initialSupplier": "Nippys",
    "sellByUnit": true,
    "sellByCarton": true,
    "regional": 33.0,
    "archive": false,
    "image": "assets/images/Nippys_Orange_Juice_450ml.png"
  },
  {
    "id": 182,
    "sku": "NAP450",
    "name": "Nippys Apple Juice 450ml",
    "description": "",
    "storageLocation": "",
    "category": "Fruit Juice",
    "metro": 30.0,
    "wholesale": 0.0,
    "price": 23.91,
    "cartonQty": 12,
    "weight": 0.0,
    "initialSupplier": "Nippys",
    "sellByUnit": true,
    "sellByCarton": true,
    "regional": 33.0,
    "archive": false,
    "image": "assets/images/Nippys_Apple_Juice_450ml.png"
  },
  {
    "id": 183,
    "sku": "NPINE450",
    "name": "Nippys Pineapple Juice 450ml",
    "description": "",
    "storageLocation": "",
    "category": "Fruit Juice",
    "metro": 30.0,
    "wholesale": 0.0,
    "price": 23.91,
    "cartonQty": 12,
    "weight": 0.0,
    "initialSupplier": "Nippys",
    "sellByUnit": true,
    "sellByCarton": true,
    "regional": 33.0,
    "archive": false,
    "image": "assets/images/Nippys_Pineapple_Juice_450ml.png"
  },
  {
    "id": 184,
    "sku": "NCHOC500",
    "name": "Nippys Chocolate 500ml",
    "description": "",
    "storageLocation": "",
    "category": "Flavoured Milk",
    "metro": 36.0,
    "wholesale": 0.0,
    "price": 30.38,
    "cartonQty": 12,
    "weight": 0.0,
    "initialSupplier": "Nippys",
    "sellByUnit": true,
    "sellByCarton": true,
    "regional": 42.0,
    "archive": false,
    "image": "assets/images/Nippys_Chocolate_500ml.png"
  },
  {
    "id": 185,
    "sku": "NCOFF500",
    "name": "Nippys Coffee 500ml",
    "description": "",
    "storageLocation": "",
    "category": "Flavoured Milk",
    "metro": 36.0,
    "wholesale": 0.0,
    "price": 30.38,
    "cartonQty": 12,
    "weight": 0.0,
    "initialSupplier": "Nippys",
    "sellByUnit": true,
    "sellByCarton": true,
    "regional": 42.0,
    "archive": false,
    "image": "assets/images/Nippys_Coffee_500ml.png"
  },
  {
    "id": 186,
    "sku": "NHCOM500",
    "name": "Nippys Honeycomb 500ml",
    "description": "",
    "storageLocation": "",
    "category": "Flavoured Milk",
    "metro": 36.0,
    "wholesale": 0.0,
    "price": 30.38,
    "cartonQty": 12,
    "weight": 0.0,
    "initialSupplier": "Nippys",
    "sellByUnit": true,
    "sellByCarton": true,
    "regional": 42.0,
    "archive": false,
    "image": "assets/images/Nippys_Honeycomb_500ml.png"
  },
  {
    "id": 187,
    "sku": "NBJ450",
    "name": "Nippys Breakfast Juice 450ml",
    "description": "",
    "storageLocation": "",
    "category": "Fruit Juice",
    "metro": 30.0,
    "wholesale": 0.0,
    "price": 23.91,
    "cartonQty": 12,
    "weight": 0.0,
    "initialSupplier": "Nippys",
    "sellByUnit": true,
    "sellByCarton": true,
    "regional": 33.0,
    "archive": false,
    "image": "assets/images/Nippys_Breakfast_Juice_450ml.png"
  },
  {
    "id": 190,
    "sku": "NCHOC375",
    "name": "Nippys Chocolate 375ml",
    "description": "",
    "storageLocation": "",
    "category": "Flavoured Milk",
    "metro": 60.0,
    "wholesale": 0.0,
    "price": 49.63,
    "cartonQty": 24,
    "weight": 0.0,
    "initialSupplier": "Nippys",
    "sellByUnit": true,
    "sellByCarton": true,
    "regional": 66.0,
    "archive": false,
    "image": "assets/images/Nippys_Chocolate_375ml.png"
  },
  {
    "id": 191,
    "sku": "NHCOM375",
    "name": "Nippys Honeycomb 375ml",
    "description": "",
    "storageLocation": "",
    "category": "Flavoured Milk",
    "metro": 60.0,
    "wholesale": 0.0,
    "price": 49.63,
    "cartonQty": 24,
    "weight": 0.0,
    "initialSupplier": "Nippys",
    "sellByUnit": true,
    "sellByCarton": true,
    "regional": 66.0,
    "archive": false,
    "image": "assets/images/Nippys_Honeycomb_375ml.png"
  },
  {
    "id": 192,
    "sku": "NVAN375",
    "name": "Nippys Vanilla Milk 375ml",
    "description": "",
    "storageLocation": "",
    "category": "Flavoured Milk",
    "metro": 60.0,
    "wholesale": 0.0,
    "price": 49.63,
    "cartonQty": 24,
    "weight": 0.0,
    "initialSupplier": "Nippys",
    "sellByUnit": true,
    "sellByCarton": true,
    "regional": 66.0,
    "archive": false,
    "image": "assets/images/Nippys_Vanilla_Milk_375ml.png"
  },
  {
    "id": 193,
    "sku": "NBANA375",
    "name": "Nippys Banana 375ml",
    "description": "",
    "storageLocation": "",
    "category": "Flavoured Milk",
    "metro": 60.0,
    "wholesale": 0.0,
    "price": 49.63,
    "cartonQty": 24,
    "weight": 0.0,
    "initialSupplier": "Nippys",
    "sellByUnit": true,
    "sellByCarton": true,
    "regional": 66.0,
    "archive": false,
    "image": "assets/images/Nippys_Banana_375ml.png"
  },
  {
    "id": 194,
    "sku": "DITP500",
    "name": "Danfels Iced Tea Peach 500ml",
    "description": "",
    "storageLocation": "",
    "category": "Iced Tea",
    "metro": 1.7,
    "wholesale": 0.0,
    "price": 1.05,
    "cartonQty": 24,
    "weight": 0.0,
    "initialSupplier": "Vinut",
    "sellByUnit": true,
    "sellByCarton": true,
    "regional": 1.8333,
    "archive": false,
    "image": "assets/images/Danfels_Iced_Tea_Peach_500ml.png"
  },
  {
    "id": 195,
    "sku": "NOP450",
    "name": "Nippys Orange & Passionfruit Juice 450ml",
    "description": "",
    "storageLocation": "",
    "category": "Fruit Juice",
    "metro": 30.0,
    "wholesale": 0.0,
    "price": 23.91,
    "cartonQty": 12,
    "weight": 0.0,
    "initialSupplier": "Nippys",
    "sellByUnit": true,
    "sellByCarton": true,
    "regional": 33.0,
    "archive": false,
    "image": "assets/images/Nippys_Orange_&_Passionfruit_Juice_450ml.png"
  },
  {
    "id": 196,
    "sku": "NSTRAW500",
    "name": "Nippys Strawberry Milk 500ml",
    "description": "",
    "storageLocation": "",
    "category": "Flavoured Milk",
    "metro": 36.0,
    "wholesale": 0.0,
    "price": 30.38,
    "cartonQty": 12,
    "weight": 0.0,
    "initialSupplier": "Nippys",
    "sellByUnit": true,
    "sellByCarton": true,
    "regional": 42.0,
    "archive": false,
    "image": "assets/images/Nippys_Strawberry_Milk_500ml.png"
  },
  {
    "id": 197,
    "sku": "DITM500",
    "name": "Danfels Iced Tea Mango 500ml",
    "description": "",
    "storageLocation": "",
    "category": "Iced Tea",
    "metro": 1.7,
    "wholesale": 0.0,
    "price": 1.05,
    "cartonQty": 24,
    "weight": 0.0,
    "initialSupplier": "Vinut",
    "sellByUnit": true,
    "sellByCarton": true,
    "regional": 1.8333,
    "archive": false,
    "image": "assets/images/Danfels_Iced_Tea_Mango_500ml.png"
  },
  {
    "id": 198,
    "sku": "RB250",
    "name": "Redbull 250ml",
    "description": "",
    "storageLocation": "",
    "category": "Energy Drink",
    "metro": 46.0,
    "wholesale": 0.0,
    "price": 40.0,
    "cartonQty": 24,
    "weight": 0.0,
    "initialSupplier": "CJM",
    "sellByUnit": false,
    "sellByCarton": true,
    "regional": 48.0,
    "archive": false,
    "image": "assets/images/Redbull_250ml.png"
  },
  {
    "id": 199,
    "sku": "VORG250",
    "name": "V Green 250ml",
    "description": "",
    "storageLocation": "",
    "category": "Energy Drink",
    "metro": 46.0,
    "wholesale": 0.0,
    "price": 38.5,
    "cartonQty": 24,
    "weight": 0.0,
    "initialSupplier": "CJM",
    "sellByUnit": false,
    "sellByCarton": true,
    "regional": 48.0,
    "archive": false,
    "image": "assets/images/V_Green_250ml.png"
  },
  {
    "id": 200,
    "sku": "VBLU250",
    "name": "V Blue 250ml",
    "description": "",
    "storageLocation": "",
    "category": "Energy Drink",
    "metro": 46.0,
    "wholesale": 0.0,
    "price": 38.5,
    "cartonQty": 24,
    "weight": 0.0,
    "initialSupplier": "CJM",
    "sellByUnit": false,
    "sellByCarton": true,
    "regional": 48.0,
    "archive": false,
    "image": "assets/images/V_Blue_250ml.png"
  },
  {
    "id": 201,
    "sku": "MORG500",
    "name": "Mother Original 500ml",
    "description": "",
    "storageLocation": "",
    "category": "Energy Drink",
    "metro": 60.0,
    "wholesale": 0.0,
    "price": 44.0,
    "cartonQty": 24,
    "weight": 0.0,
    "initialSupplier": "CJM",
    "sellByUnit": false,
    "sellByCarton": true,
    "regional": 60.0,
    "archive": false,
    "image": "assets/images/Mother_Original_500ml.png"
  },
  {
    "id": 202,
    "sku": "MFW600",
    "name": "Mount Franklin Water 600ml",
    "description": "",
    "storageLocation": "",
    "category": "Water",
    "metro": 22.5,
    "wholesale": 0.0,
    "price": 19.5,
    "cartonQty": 24,
    "weight": 0.0,
    "initialSupplier": "CJM",
    "sellByUnit": false,
    "sellByCarton": true,
    "regional": 25.92,
    "archive": false,
    "image": "assets/images/Mount_Franklin_Water_600ml.png"
  },
  {
    "id": 203,
    "sku": "DITL500",
    "name": "Danfels Iced Tea Lemon 500ml",
    "description": "",
    "storageLocation": "",
    "category": "Iced Tea",
    "metro": 1.7,
    "wholesale": 0.0,
    "price": 1.05,
    "cartonQty": 12,
    "weight": 0.0,
    "initialSupplier": "Vinut",
    "sellByUnit": true,
    "sellByCarton": true,
    "regional": 1.8333,
    "archive": false,
    "image": "assets/images/Danfels_Iced_Tea_Lemon_500ml.png"
  },
  {
    "id": 204,
    "sku": "NSTRAW375",
    "name": "Nippys Strawberry Milk 375ml",
    "description": "",
    "storageLocation": "",
    "category": "Flavoured Milk",
    "metro": 60.0,
    "wholesale": 0.0,
    "price": 49.63,
    "cartonQty": 24,
    "weight": 0.0,
    "initialSupplier": "Nippys",
    "sellByUnit": true,
    "sellByCarton": true,
    "regional": 66.0,
    "archive": false,
    "image": "assets/images/Nippys_Strawberry_Milk_375ml.png"
  },
  {
    "id": 205,
    "sku": "NCOFF375",
    "name": "Nippys Coffee 375ml",
    "description": "",
    "storageLocation": "",
    "category": "Flavoured Milk",
    "metro": 60.0,
    "wholesale": 0.0,
    "price": 49.63,
    "cartonQty": 24,
    "weight": 0.0,
    "initialSupplier": "Nippys",
    "sellByUnit": true,
    "sellByCarton": true,
    "regional": 66.0,
    "archive": false,
    "image": "assets/images/Nippys_Coffee_375ml.png"
  },
  {
    "id": 206,
    "sku": "PEPM600",
    "name": "Pepsi Max 600ml",
    "description": "",
    "storageLocation": "",
    "category": "Soft Drink",
    "metro": 56.0,
    "wholesale": 0.0,
    "price": 50.0,
    "cartonQty": 24,
    "weight": 0.0,
    "initialSupplier": "CJM",
    "sellByUnit": false,
    "sellByCarton": true,
    "regional": 60.0,
    "archive": false,
    "image": "assets/images/Pepsi_Max_600ml.png"
  },
  {
    "id": 207,
    "sku": "PASS600",
    "name": "Passiona 600ml",
    "description": "",
    "storageLocation": "",
    "category": "Soft Drink",
    "metro": 56.0,
    "wholesale": 0.0,
    "price": 50.0,
    "cartonQty": 24,
    "weight": 0.0,
    "initialSupplier": "CJM",
    "sellByUnit": false,
    "sellByCarton": true,
    "regional": 60.0,
    "archive": false,
    "image": "assets/images/Passiona_600ml.png"
  },
  {
    "id": 208,
    "sku": "NOM450",
    "name": "Nippys Orange & Mango Juice 450ml",
    "description": "",
    "storageLocation": "",
    "category": "Fruit Juice",
    "metro": 30.0,
    "wholesale": 0.0,
    "price": 23.91,
    "cartonQty": 12,
    "weight": 0.0,
    "initialSupplier": "Nippys",
    "sellByUnit": true,
    "sellByCarton": true,
    "regional": 33.0,
    "archive": false,
    "image": "assets/images/Nippys_Orange_&_Mango_Juice_450ml.png"
  },
  {
    "id": 213,
    "sku": "NABC450",
    "name": "Nippys Apple Blackcurrant Juice 450ml",
    "description": "",
    "storageLocation": "",
    "category": "Fruit Juice",
    "metro": 30.0,
    "wholesale": 0.0,
    "price": 23.91,
    "cartonQty": 12,
    "weight": 0.0,
    "initialSupplier": "Nippys",
    "sellByUnit": true,
    "sellByCarton": true,
    "regional": 33.0,
    "archive": false,
    "image": "assets/images/Nippys_Apple_Blackcurrant_Juice_450ml.png"
  },
  {
    "id": 214,
    "sku": "RB473",
    "name": "Redbull 473ml",
    "description": "",
    "storageLocation": "",
    "category": "Energy Drink",
    "metro": 44.0,
    "wholesale": 0.0,
    "price": 38.0,
    "cartonQty": 12,
    "weight": 0.0,
    "initialSupplier": "CJM",
    "sellByUnit": false,
    "sellByCarton": true,
    "regional": 46.0,
    "archive": false,
    "image": "assets/images/Redbull_473ml.png"
  },
  {
    "id": 218,
    "sku": "NOJ1L",
    "name": "Nippys Orange Juice 1L",
    "description": "",
    "storageLocation": "",
    "category": "Fruit Juice",
    "metro": 27.0,
    "wholesale": 0.0,
    "price": 20.64,
    "cartonQty": 6,
    "weight": 0.0,
    "initialSupplier": "Nippys",
    "sellByUnit": true,
    "sellByCarton": true,
    "regional": 30.0,
    "archive": false,
    "image": "assets/images/Nippys_Orange_Juice_1L.png"
  },
  {
    "id": 219,
    "sku": "NAP1L",
    "name": "Nippys Apple Juice 1L",
    "description": "",
    "storageLocation": "",
    "category": "Fruit Juice",
    "metro": 27.0,
    "wholesale": 0.0,
    "price": 20.64,
    "cartonQty": 6,
    "weight": 0.0,
    "initialSupplier": "Nippys",
    "sellByUnit": true,
    "sellByCarton": true,
    "regional": 30.0,
    "archive": false,
    "image": "assets/images/Nippys_Apple_Juice_1L.png"
  },
  {
    "id": 220,
    "sku": "NAP2L",
    "name": "Nippys Apple Juice 2L",
    "description": "",
    "storageLocation": "",
    "category": "Fruit Juice",
    "metro": 31.2,
    "wholesale": 0.0,
    "price": 27.64,
    "cartonQty": 6,
    "weight": 0.0,
    "initialSupplier": "Nippys",
    "sellByUnit": true,
    "sellByCarton": true,
    "regional": 34.02,
    "archive": false,
    "image": "assets/images/Nippys_Apple_Juice_2L.png"
  },
  {
    "id": 221,
    "sku": "NOJ2L",
    "name": "Nippys Orange Juice 2L",
    "description": "",
    "storageLocation": "",
    "category": "Fruit Juice",
    "metro": 31.2,
    "wholesale": 0.0,
    "price": 27.64,
    "cartonQty": 6,
    "weight": 0.0,
    "initialSupplier": "Nippys",
    "sellByUnit": false,
    "sellByCarton": true,
    "regional": 34.02,
    "archive": false,
    "image": "assets/images/Nippys_Orange_Juice_2L.png"
  },
  {
    "id": 222,
    "sku": "NOM2L",
    "name": "Nippys Orange & Mango Juice 2L",
    "description": "",
    "storageLocation": "",
    "category": "Fruit Juice",
    "metro": 31.2,
    "wholesale": 0.0,
    "price": 27.64,
    "cartonQty": 6,
    "weight": 0.0,
    "initialSupplier": "Nippys",
    "sellByUnit": false,
    "sellByCarton": true,
    "regional": 34.02,
    "archive": false,
    "image": "assets/images/Nippys_Orange_&_Mango_Juice_2L.png"
  },
  {
    "id": 223,
    "sku": "NABC2L",
    "name": "Nippys Apple Blackcurrant Juice 2L",
    "description": "",
    "storageLocation": "",
    "category": "Fruit Juice",
    "metro": 31.2,
    "wholesale": 0.0,
    "price": 27.64,
    "cartonQty": 6,
    "weight": 0.0,
    "initialSupplier": "Nippys",
    "sellByUnit": false,
    "sellByCarton": true,
    "regional": 34.02,
    "archive": false,
    "image": "assets/images/Nippys_Apple_Blackcurrant_Juice_2L.png"
  },
  {
    "id": 224,
    "sku": "NPINE2L",
    "name": "Nippys Pineapple Juice 2L",
    "description": "",
    "storageLocation": "",
    "category": "Fruit Juice",
    "metro": 31.2,
    "wholesale": 0.0,
    "price": 27.64,
    "cartonQty": 6,
    "weight": 0.0,
    "initialSupplier": "Nippys",
    "sellByUnit": false,
    "sellByCarton": true,
    "regional": 34.02,
    "archive": false,
    "image": "assets/images/Nippys_Pineapple_Juice_2L.png"
  },
  {
    "id": 225,
    "sku": "NBJ2L",
    "name": "Nippys Breakfast Juice 2L",
    "description": "",
    "storageLocation": "",
    "category": "Fruit Juice",
    "metro": 31.2,
    "wholesale": 0.0,
    "price": 27.64,
    "cartonQty": 6,
    "weight": 0.0,
    "initialSupplier": "Nippys",
    "sellByUnit": false,
    "sellByCarton": true,
    "regional": 34.02,
    "archive": false,
    "image": "assets/images/Nippys_Breakfast_Juice_2L.png"
  },
  {
    "id": 226,
    "sku": "NUNSOJ2L",
    "name": "Nippys Orange Unsweet Juice 2L",
    "description": "",
    "storageLocation": "",
    "category": "Fruit Juice",
    "metro": 31.2,
    "wholesale": 0.0,
    "price": 27.64,
    "cartonQty": 6,
    "weight": 0.0,
    "initialSupplier": "Nippys",
    "sellByUnit": false,
    "sellByCarton": true,
    "regional": 34.02,
    "archive": false,
    "image": "assets/images/Nippys_Orange_Unsweet_Juice_2L.png"
  },
  {
    "id": 227,
    "sku": "NLQ450",
    "name": "Nippys Lemon Quencher 450ml",
    "description": "",
    "storageLocation": "",
    "category": "Fruit Juice",
    "metro": 30.0,
    "wholesale": 0.0,
    "price": 20.306,
    "cartonQty": 12,
    "weight": 0.0,
    "initialSupplier": "Nippys",
    "sellByUnit": true,
    "sellByCarton": true,
    "regional": 33.0,
    "archive": false,
    "image": "assets/images/Nippys_Lemon_Quencher_450ml.png"
  },
  {
    "id": 228,
    "sku": "NBOQ450",
    "name": "Nippys Blood Orange Quencher 450ml",
    "description": "",
    "storageLocation": "",
    "category": "Fruit Juice",
    "metro": 30.0,
    "wholesale": 0.0,
    "price": 20.306,
    "cartonQty": 12,
    "weight": 0.0,
    "initialSupplier": "Nippys",
    "sellByUnit": true,
    "sellByCarton": true,
    "regional": 33.0,
    "archive": false,
    "image": "assets/images/Nippys_Blood_Orange_Quencher_450ml.png"
  },
  {
    "id": 229,
    "sku": "SUNK600",
    "name": "Sunkist 600ml",
    "description": "",
    "storageLocation": "",
    "category": "Soft Drink",
    "metro": 56.0,
    "wholesale": 0.0,
    "price": 50.0,
    "cartonQty": 24,
    "weight": 0.0,
    "initialSupplier": "CJM",
    "sellByUnit": false,
    "sellByCarton": true,
    "regional": 60.0,
    "archive": false,
    "image": "assets/images/Sunkist_600ml.png"
  },
  {
    "id": 230,
    "sku": "",
    "name": "Kids",
    "description": "",
    "storageLocation": "",
    "category": "Fruit Juice",
    "metro": 0.0,
    "wholesale": 0.0,
    "price": 0.0,
    "cartonQty": 1,
    "weight": 0.0,
    "initialSupplier": "",
    "sellByUnit": true,
    "sellByCarton": false,
    "regional": 0.0,
    "archive": false,
    "image": "assets/images/Kids.png"
  },
  {
    "id": 231,
    "sku": "PEP600",
    "name": "Pepsi 600ml",
    "description": "",
    "storageLocation": "",
    "category": "Soft Drink",
    "metro": 56.0,
    "wholesale": 0.0,
    "price": 50.0,
    "cartonQty": 24,
    "weight": 0.0,
    "initialSupplier": "CJM",
    "sellByUnit": false,
    "sellByCarton": true,
    "regional": 60.0,
    "archive": false,
    "image": "assets/images/Pepsi_600ml.png"
  },
  {
    "id": 232,
    "sku": "VBLU500",
    "name": "V Blue 500ml",
    "description": "",
    "storageLocation": "",
    "category": "Energy Drink",
    "metro": 68.0,
    "wholesale": 0.0,
    "price": 59.0,
    "cartonQty": 24,
    "weight": 0.0,
    "initialSupplier": "CJM",
    "sellByUnit": false,
    "sellByCarton": true,
    "regional": 72.0,
    "archive": false,
    "image": "assets/images/V_Blue_500ml.png"
  },
  {
    "id": 233,
    "sku": "OZW15",
    "name": "Oz Water 1.5L",
    "description": "",
    "storageLocation": "",
    "category": "Water",
    "metro": 15.0,
    "wholesale": 0.0,
    "price": 10.0,
    "cartonQty": 12,
    "weight": 0.0,
    "initialSupplier": "Nippys",
    "sellByUnit": false,
    "sellByCarton": true,
    "regional": 18.0,
    "archive": false,
    "image": "assets/images/Oz_Water_1.5L.png"
  },
  {
    "id": 234,
    "sku": "NCHOC1L",
    "name": "Nippys Chocolate 1L",
    "description": "",
    "storageLocation": "",
    "category": "Flavoured Milk",
    "metro": 27.0,
    "wholesale": 0.0,
    "price": 23.26,
    "cartonQty": 6,
    "weight": 0.0,
    "initialSupplier": "Nippys",
    "sellByUnit": false,
    "sellByCarton": true,
    "regional": 33.0,
    "archive": false,
    "image": "assets/images/Nippys_Chocolate_1L.png"
  },
  {
    "id": 235,
    "sku": "NCOFF1L",
    "name": "Nippys Coffee 1L",
    "description": "",
    "storageLocation": "",
    "category": "Flavoured Milk",
    "metro": 27.0,
    "wholesale": 0.0,
    "price": 23.26,
    "cartonQty": 6,
    "weight": 0.0,
    "initialSupplier": "Nippys",
    "sellByUnit": false,
    "sellByCarton": true,
    "regional": 33.0,
    "archive": false,
    "image": "assets/images/Nippys_Coffee_1L.png"
  },
  {
    "id": 237,
    "sku": "NPFOJ2L",
    "name": "Nippys Pulp Free Orange Juice 2L",
    "description": "",
    "storageLocation": "",
    "category": "Fruit Juice",
    "metro": 31.2,
    "wholesale": 0.0,
    "price": 27.64,
    "cartonQty": 6,
    "weight": 0.0,
    "initialSupplier": "Nippys",
    "sellByUnit": false,
    "sellByCarton": true,
    "regional": 34.02,
    "archive": false,
    "image": "assets/images/Nippys_Pulp_Free_Orange_Juice_2L.png"
  },
  {
    "id": 238,
    "sku": "NOP2L",
    "name": "Nippys Orange & Passionfruit Juice 2L",
    "description": "",
    "storageLocation": "",
    "category": "Fruit Juice",
    "metro": 31.2,
    "wholesale": 0.0,
    "price": 27.64,
    "cartonQty": 6,
    "weight": 0.0,
    "initialSupplier": "Nippys",
    "sellByUnit": false,
    "sellByCarton": true,
    "regional": 34.02,
    "archive": false,
    "image": "assets/images/Nippys_Orange_&_Passionfruit_Juice_2L.png"
  },
  {
    "id": 240,
    "sku": "VORG500",
    "name": "V Green 500ml",
    "description": "",
    "storageLocation": "",
    "category": "Energy Drink",
    "metro": 68.0,
    "wholesale": 0.0,
    "price": 59.0,
    "cartonQty": 24,
    "weight": 0.0,
    "initialSupplier": "CJM",
    "sellByUnit": false,
    "sellByCarton": true,
    "regional": 72.0,
    "archive": false,
    "image": "assets/images/V_Green_500ml.png"
  },
  {
    "id": 241,
    "sku": "",
    "name": "Nippys Double Espresso 500ml",
    "description": "",
    "storageLocation": "",
    "category": "Flavoured Milk",
    "metro": 0.0,
    "wholesale": 0.0,
    "price": 0.0,
    "cartonQty": 1,
    "weight": 0.0,
    "initialSupplier": "",
    "sellByUnit": true,
    "sellByCarton": false,
    "regional": 0.0,
    "archive": false,
    "image": "assets/images/Nippys_Double_Espresso_500ml.png"
  },
  {
    "id": 242,
    "sku": "",
    "name": "Nippys Mineral Water Orange 600ml",
    "description": "",
    "storageLocation": "",
    "category": "Mineral Water",
    "metro": 0.0,
    "wholesale": 0.0,
    "price": 0.0,
    "cartonQty": 1,
    "weight": 0.0,
    "initialSupplier": "",
    "sellByUnit": true,
    "sellByCarton": false,
    "regional": 0.0,
    "archive": false,
    "image": "assets/images/Nippys_Mineral_Water_Orange_600ml.png"
  },
  {
    "id": 243,
    "sku": "",
    "name": "Nippys Mineral Water Paradise Punch 600ml",
    "description": "",
    "storageLocation": "",
    "category": "Mineral Water",
    "metro": 0.0,
    "wholesale": 0.0,
    "price": 0.0,
    "cartonQty": 1,
    "weight": 0.0,
    "initialSupplier": "",
    "sellByUnit": true,
    "sellByCarton": false,
    "regional": 0.0,
    "archive": false,
    "image": "assets/images/Nippys_Mineral_Water_Paradise_Punch_600ml.png"
  },
  {
    "id": 244,
    "sku": "",
    "name": "Nippys Mineral Water Lime 600ml",
    "description": "",
    "storageLocation": "",
    "category": "Mineral Water",
    "metro": 0.0,
    "wholesale": 0.0,
    "price": 0.0,
    "cartonQty": 1,
    "weight": 0.0,
    "initialSupplier": "",
    "sellByUnit": true,
    "sellByCarton": false,
    "regional": 0.0,
    "archive": false,
    "image": "assets/images/Nippys_Mineral_Water_Lime_600ml.png"
  },
  {
    "id": 245,
    "sku": "",
    "name": "Nippys Mineral Water Portello 600ml",
    "description": "",
    "storageLocation": "",
    "category": "Mineral Water",
    "metro": 0.0,
    "wholesale": 0.0,
    "price": 0.0,
    "cartonQty": 1,
    "weight": 0.0,
    "initialSupplier": "",
    "sellByUnit": true,
    "sellByCarton": false,
    "regional": 0.0,
    "archive": false,
    "image": "assets/images/Nippys_Mineral_Water_Portello_600ml.png"
  },
  {
    "id": 248,
    "sku": "",
    "name": "Nippys Cloudy Apple Juice 1L",
    "description": "",
    "storageLocation": "",
    "category": "Unknown",
    "metro": 0.0,
    "wholesale": 0.0,
    "price": 0.0,
    "cartonQty": 1,
    "weight": 0.0,
    "initialSupplier": "",
    "sellByUnit": true,
    "sellByCarton": false,
    "regional": 0.0,
    "archive": false,
    "image": "assets/images/Nippys_Cloudy_Apple_Juice_1L.png"
  },
  {
    "id": 250,
    "sku": "OZW600",
    "name": "Oz Water 600ml",
    "description": "",
    "storageLocation": "",
    "category": "Water",
    "metro": 15.0,
    "wholesale": 0.0,
    "price": 10.0,
    "cartonQty": 24,
    "weight": 0.0,
    "initialSupplier": "Nippys",
    "sellByUnit": false,
    "sellByCarton": true,
    "regional": 18.0,
    "archive": false,
    "image": "assets/images/Oz_Water_600ml.png"
  },
  {
    "id": 251,
    "sku": "",
    "name": "Nippys Mixed Milk 375ml",
    "description": "",
    "storageLocation": "",
    "category": "Unknown",
    "metro": 0.0,
    "wholesale": 0.0,
    "price": 0.0,
    "cartonQty": 1,
    "weight": 0.0,
    "initialSupplier": "",
    "sellByUnit": true,
    "sellByCarton": false,
    "regional": 0.0,
    "archive": false,
    "image": "assets/images/Nippys_Mixed_Milk_375ml.png"
  },
  {
    "id": 252,
    "sku": "NLEM2L",
    "name": "Nippys Lemon Juice 2L",
    "description": "",
    "storageLocation": "",
    "category": "Fruit Juice",
    "metro": 31.2,
    "wholesale": 0.0,
    "price": 27.37,
    "cartonQty": 6,
    "weight": 0.0,
    "initialSupplier": "Nippys",
    "sellByUnit": false,
    "sellByCarton": true,
    "regional": 34.02,
    "archive": false,
    "image": "assets/images/Nippys_Lemon_Juice_2L.png"
  },
  {
    "id": 253,
    "sku": "",
    "name": "Nippys Mineral Water Lemon 600ml",
    "description": "",
    "storageLocation": "",
    "category": "Mineral Water",
    "metro": 0.0,
    "wholesale": 0.0,
    "price": 0.0,
    "cartonQty": 1,
    "weight": 0.0,
    "initialSupplier": "",
    "sellByUnit": true,
    "sellByCarton": false,
    "regional": 0.0,
    "archive": false,
    "image": "assets/images/Nippys_Mineral_Water_Lemon_600ml.png"
  },
  {
    "id": 254,
    "sku": "",
    "name": "Nippys Mineral Water Apple Raspberry 600ml",
    "description": "",
    "storageLocation": "",
    "category": "Mineral Water",
    "metro": 0.0,
    "wholesale": 0.0,
    "price": 0.0,
    "cartonQty": 1,
    "weight": 0.0,
    "initialSupplier": "",
    "sellByUnit": true,
    "sellByCarton": false,
    "regional": 0.0,
    "archive": false,
    "image": "assets/images/Nippys_Mineral_Water_Apple_Raspberry_600ml.png"
  },
  {
    "id": 255,
    "sku": "",
    "name": "Nippys Mineral Water Natural 600ml",
    "description": "",
    "storageLocation": "",
    "category": "Mineral Water",
    "metro": 0.0,
    "wholesale": 0.0,
    "price": 0.0,
    "cartonQty": 1,
    "weight": 0.0,
    "initialSupplier": "",
    "sellByUnit": true,
    "sellByCarton": false,
    "regional": 0.0,
    "archive": false,
    "image": "assets/images/Nippys_Mineral_Water_Natural_600ml.png"
  },
  {
    "id": 256,
    "sku": "MDEW600",
    "name": "Mountain Dew 600ml",
    "description": "",
    "storageLocation": "",
    "category": "Soft Drink",
    "metro": 56.0,
    "wholesale": 0.0,
    "price": 50.0,
    "cartonQty": 24,
    "weight": 0.0,
    "initialSupplier": "CJM",
    "sellByUnit": false,
    "sellByCarton": true,
    "regional": 60.0,
    "archive": false,
    "image": "assets/images/Mountain_Dew_600ml.png"
  },
  {
    "id": 257,
    "sku": "NBJ1L",
    "name": "Nippys Breakfast Juice 1L",
    "description": "",
    "storageLocation": "",
    "category": "Fruit Juice",
    "metro": 27.0,
    "wholesale": 0.0,
    "price": 20.64,
    "cartonQty": 6,
    "weight": 0.0,
    "initialSupplier": "Nippys",
    "sellByUnit": false,
    "sellByCarton": true,
    "regional": 30.0,
    "archive": false,
    "image": "assets/images/Nippys_Breakfast_Juice_1L.png"
  },
  {
    "id": 260,
    "sku": "LEM600",
    "name": "Lemonade 600ml",
    "description": "",
    "storageLocation": "",
    "category": "Soft Drink",
    "metro": 56.0,
    "wholesale": 0.0,
    "price": 50.0,
    "cartonQty": 24,
    "weight": 0.0,
    "initialSupplier": "CJM",
    "sellByUnit": false,
    "sellByCarton": true,
    "regional": 60.0,
    "archive": false,
    "image": "assets/images/Lemonade_600ml.png"
  },
  {
    "id": 261,
    "sku": "SOLO600",
    "name": "Solo 600ml",
    "description": "",
    "storageLocation": "",
    "category": "Soft Drink",
    "metro": 56.0,
    "wholesale": 0.0,
    "price": 50.0,
    "cartonQty": 24,
    "weight": 0.0,
    "initialSupplier": "CJM",
    "sellByUnit": false,
    "sellByCarton": true,
    "regional": 60.0,
    "archive": false,
    "image": "assets/images/Solo_600ml.png"
  },
  {
    "id": 262,
    "sku": "",
    "name": "V Blue Can 500ml",
    "description": "",
    "storageLocation": "",
    "category": "Energy Drink",
    "metro": 0.0,
    "wholesale": 0.0,
    "price": 0.0,
    "cartonQty": 1,
    "weight": 0.0,
    "initialSupplier": "",
    "sellByUnit": true,
    "sellByCarton": false,
    "regional": 0.0,
    "archive": false,
    "image": "assets/images/V_Blue_Can_500ml.png"
  },
  {
    "id": 263,
    "sku": "COC600",
    "name": "Coke Classic 600ml",
    "description": "",
    "storageLocation": "",
    "category": "Soft Drink",
    "metro": 52.0,
    "wholesale": 0.0,
    "price": 44.0,
    "cartonQty": 24,
    "weight": 0.0,
    "initialSupplier": "CCA",
    "sellByUnit": false,
    "sellByCarton": true,
    "regional": 54.0,
    "archive": false,
    "image": "assets/images/Coke_Classic_600ml.png"
  },
  {
    "id": 264,
    "sku": "",
    "name": "Coke Zero 600ml",
    "description": "",
    "storageLocation": "",
    "category": "Soft Drink",
    "metro": 0.0,
    "wholesale": 0.0,
    "price": 0.0,
    "cartonQty": 1,
    "weight": 0.0,
    "initialSupplier": "",
    "sellByUnit": true,
    "sellByCarton": false,
    "regional": 0.0,
    "archive": false,
    "image": "assets/images/Coke_Zero_600ml.png"
  },
  {
    "id": 265,
    "sku": "",
    "name": "Maximus Raspberry 1L",
    "description": "",
    "storageLocation": "",
    "category": "Energy Drink",
    "metro": 0.0,
    "wholesale": 0.0,
    "price": 0.0,
    "cartonQty": 1,
    "weight": 0.0,
    "initialSupplier": "",
    "sellByUnit": true,
    "sellByCarton": false,
    "regional": 0.0,
    "archive": false,
    "image": "assets/images/Maximus_Raspberry_1L.png"
  },
  {
    "id": 266,
    "sku": "",
    "name": "Maximus Lemonade 1L",
    "description": "",
    "storageLocation": "",
    "category": "Energy Drink",
    "metro": 0.0,
    "wholesale": 0.0,
    "price": 0.0,
    "cartonQty": 1,
    "weight": 0.0,
    "initialSupplier": "",
    "sellByUnit": true,
    "sellByCarton": false,
    "regional": 0.0,
    "archive": false,
    "image": "assets/images/Maximus_Lemonade_1L.png"
  },
  {
    "id": 267,
    "sku": "",
    "name": "Maximus Blue 1L",
    "description": "",
    "storageLocation": "",
    "category": "Energy Drink",
    "metro": 0.0,
    "wholesale": 0.0,
    "price": 0.0,
    "cartonQty": 1,
    "weight": 0.0,
    "initialSupplier": "",
    "sellByUnit": true,
    "sellByCarton": false,
    "regional": 0.0,
    "archive": false,
    "image": "assets/images/Maximus_Blue_1L.png"
  },
  {
    "id": 268,
    "sku": "",
    "name": "Maximus Grape 1L",
    "description": "",
    "storageLocation": "",
    "category": "Energy Drink",
    "metro": 0.0,
    "wholesale": 0.0,
    "price": 0.0,
    "cartonQty": 1,
    "weight": 0.0,
    "initialSupplier": "",
    "sellByUnit": true,
    "sellByCarton": false,
    "regional": 0.0,
    "archive": false,
    "image": "assets/images/Maximus_Grape_1L.png"
  },
  {
    "id": 269,
    "sku": "",
    "name": "Maximus Mango/Passionfruit 1L",
    "description": "",
    "storageLocation": "",
    "category": "Energy Drink",
    "metro": 0.0,
    "wholesale": 0.0,
    "price": 0.0,
    "cartonQty": 1,
    "weight": 0.0,
    "initialSupplier": "",
    "sellByUnit": true,
    "sellByCarton": false,
    "regional": 0.0,
    "archive": false,
    "image": "assets/images/Maximus_Mango_Passionfruit_1L.png"
  },
  {
    "id": 270,
    "sku": "NBO1L",
    "name": "Nippys Blood Orange Juice 1L",
    "description": "",
    "storageLocation": "",
    "category": "Fruit Juice",
    "metro": 30.0,
    "wholesale": 0.0,
    "price": 23.63,
    "cartonQty": 6,
    "weight": 0.0,
    "initialSupplier": "Nippys",
    "sellByUnit": false,
    "sellByCarton": true,
    "regional": 30.6,
    "archive": false,
    "image": "assets/images/Nippys_Blood_Orange_Juice_1L.png"
  },
  {
    "id": 271,
    "sku": "VORG350",
    "name": "V Green (Glass) 350ml",
    "description": "",
    "storageLocation": "",
    "category": "Energy Drink",
    "metro": 72.0,
    "wholesale": 0.0,
    "price": 62.0,
    "cartonQty": 24,
    "weight": 0.0,
    "initialSupplier": "CJM",
    "sellByUnit": false,
    "sellByCarton": true,
    "regional": 76.0,
    "archive": false,
    "image": "assets/images/V_Green_(Glass)_350ml.png"
  },
  {
    "id": 272,
    "sku": "",
    "name": "Nippys Chocolate 250ml",
    "description": "",
    "storageLocation": "",
    "category": "Flavoured Milk",
    "metro": 0.0,
    "wholesale": 0.0,
    "price": 0.0,
    "cartonQty": 1,
    "weight": 0.0,
    "initialSupplier": "",
    "sellByUnit": true,
    "sellByCarton": false,
    "regional": 0.0,
    "archive": false,
    "image": "assets/images/Nippys_Chocolate_250ml.png"
  },
  {
    "id": 273,
    "sku": "",
    "name": "Nippys Coffee 250ml",
    "description": "",
    "storageLocation": "",
    "category": "Flavoured Milk",
    "metro": 0.0,
    "wholesale": 0.0,
    "price": 0.0,
    "cartonQty": 1,
    "weight": 0.0,
    "initialSupplier": "",
    "sellByUnit": true,
    "sellByCarton": false,
    "regional": 0.0,
    "archive": false,
    "image": "assets/images/Nippys_Coffee_250ml.png"
  },
  {
    "id": 275,
    "sku": "",
    "name": "Nippys Mocha 375ml",
    "description": "",
    "storageLocation": "",
    "category": "Unknown",
    "metro": 0.0,
    "wholesale": 0.0,
    "price": 0.0,
    "cartonQty": 1,
    "weight": 0.0,
    "initialSupplier": "",
    "sellByUnit": true,
    "sellByCarton": false,
    "regional": 0.0,
    "archive": false,
    "image": "assets/images/Nippys_Mocha_375ml.png"
  },
  {
    "id": 277,
    "sku": "NOJ375",
    "name": "Nippys Orange Juice 375ml",
    "description": "",
    "storageLocation": "",
    "category": "Fruit Juice",
    "metro": 30.0,
    "wholesale": 0.0,
    "price": 24.5,
    "cartonQty": 12,
    "weight": 0.0,
    "initialSupplier": "Nippys",
    "sellByUnit": false,
    "sellByCarton": true,
    "regional": 33.0,
    "archive": false,
    "image": "assets/images/Nippys_Orange_Juice_375ml.png"
  },
  {
    "id": 278,
    "sku": "NAP375",
    "name": "Nippys Apple Juice 375ml",
    "description": "",
    "storageLocation": "",
    "category": "Fruit Juice",
    "metro": 30.0,
    "wholesale": 0.0,
    "price": 24.5,
    "cartonQty": 12,
    "weight": 0.0,
    "initialSupplier": "Nippys",
    "sellByUnit": false,
    "sellByCarton": true,
    "regional": 33.0,
    "archive": false,
    "image": "assets/images/Nippys_Apple_Juice_375ml.png"
  },
  {
    "id": 279,
    "sku": "NBJ375",
    "name": "Nippys Breakfast Juice 375ml",
    "description": "",
    "storageLocation": "",
    "category": "Fruit Juice",
    "metro": 30.0,
    "wholesale": 0.0,
    "price": 24.5,
    "cartonQty": 12,
    "weight": 0.0,
    "initialSupplier": "Nippys",
    "sellByUnit": false,
    "sellByCarton": true,
    "regional": 33.0,
    "archive": false,
    "image": "assets/images/Nippys_Breakfast_Juice_375ml.png"
  },
  {
    "id": 282,
    "sku": "NABC375",
    "name": "Nippys Apple Blackcurrant Juice 375ml",
    "description": "",
    "storageLocation": "",
    "category": "Fruit Juice",
    "metro": 30.0,
    "wholesale": 0.0,
    "price": 24.5,
    "cartonQty": 12,
    "weight": 0.0,
    "initialSupplier": "Nippys",
    "sellByUnit": false,
    "sellByCarton": true,
    "regional": 33.0,
    "archive": false,
    "image": "assets/images/Nippys_Apple_Blackcurrant_Juice_375ml.png"
  },
  {
    "id": 283,
    "sku": "",
    "name": "Nippys Cranberry Juice 2L",
    "description": "",
    "storageLocation": "",
    "category": "Fruit Juice",
    "metro": 0.0,
    "wholesale": 0.0,
    "price": 0.0,
    "cartonQty": 1,
    "weight": 0.0,
    "initialSupplier": "",
    "sellByUnit": true,
    "sellByCarton": false,
    "regional": 0.0,
    "archive": false,
    "image": "assets/images/Nippys_Cranberry_Juice_2L.png"
  },
  {
    "id": 284,
    "sku": "NOJ350",
    "name": "Nippys Orange Juice 350ml",
    "description": "",
    "storageLocation": "",
    "category": "Fruit Juice",
    "metro": 34.0,
    "wholesale": 0.0,
    "price": 25.0,
    "cartonQty": 12,
    "weight": 0.0,
    "initialSupplier": "Nippys",
    "sellByUnit": false,
    "sellByCarton": true,
    "regional": 35.4,
    "archive": false,
    "image": "assets/images/Nippys_Orange_Juice_350ml.png"
  },
  {
    "id": 285,
    "sku": "NAP350",
    "name": "Nippys Apple Juice 350ml",
    "description": "",
    "storageLocation": "",
    "category": "Fruit Juice",
    "metro": 34.0,
    "wholesale": 0.0,
    "price": 25.0,
    "cartonQty": 12,
    "weight": 0.0,
    "initialSupplier": "Nippys",
    "sellByUnit": false,
    "sellByCarton": true,
    "regional": 35.4,
    "archive": false,
    "image": "assets/images/Nippys_Apple_Juice_350ml.png"
  },
  {
    "id": 286,
    "sku": "NW750",
    "name": "Nippys Water 750ml",
    "description": "",
    "storageLocation": "",
    "category": "Water",
    "metro": 25.6,
    "wholesale": 0.0,
    "price": 20.6,
    "cartonQty": 20,
    "weight": 0.0,
    "initialSupplier": "Nippys",
    "sellByUnit": false,
    "sellByCarton": true,
    "regional": 28.0,
    "archive": false,
    "image": "assets/images/Nippys_Water_750ml.png"
  },
  {
    "id": 288,
    "sku": "",
    "name": "Danfels Mixed Box 500ml",
    "description": "",
    "storageLocation": "",
    "category": "Unknown",
    "metro": 0.0,
    "wholesale": 0.0,
    "price": 0.0,
    "cartonQty": 1,
    "weight": 0.0,
    "initialSupplier": "",
    "sellByUnit": true,
    "sellByCarton": false,
    "regional": 0.0,
    "archive": false,
    "image": "assets/images/Danfels_Mixed_Box_500ml.png"
  },
  {
    "id": 289,
    "sku": "",
    "name": "Nippys Mixed Box 375ml",
    "description": "",
    "storageLocation": "",
    "category": "Flavoured Milk",
    "metro": 0.0,
    "wholesale": 0.0,
    "price": 0.0,
    "cartonQty": 1,
    "weight": 0.0,
    "initialSupplier": "",
    "sellByUnit": true,
    "sellByCarton": false,
    "regional": 0.0,
    "archive": false,
    "image": "assets/images/Nippys_Mixed_Box_375ml.png"
  },
  {
    "id": 290,
    "sku": "",
    "name": "Nippys Mixed 375ml",
    "description": "",
    "storageLocation": "",
    "category": "Flavoured Milk",
    "metro": 0.0,
    "wholesale": 0.0,
    "price": 0.0,
    "cartonQty": 1,
    "weight": 0.0,
    "initialSupplier": "",
    "sellByUnit": true,
    "sellByCarton": false,
    "regional": 0.0,
    "archive": false,
    "image": "assets/images/Nippys_Mixed_375ml.png"
  },
  {
    "id": 291,
    "sku": "",
    "name": "Nippys Mixed 500ml",
    "description": "",
    "storageLocation": "",
    "category": "Unknown",
    "metro": 0.0,
    "wholesale": 0.0,
    "price": 0.0,
    "cartonQty": 1,
    "weight": 0.0,
    "initialSupplier": "",
    "sellByUnit": true,
    "sellByCarton": false,
    "regional": 0.0,
    "archive": false,
    "image": "assets/images/Nippys_Mixed_500ml.png"
  },
  {
    "id": 292,
    "sku": "NMIX450",
    "name": "Nippys Mixed Juice 450ml",
    "description": "",
    "storageLocation": "",
    "category": "Fruit Juice",
    "metro": 30.0,
    "wholesale": 0.0,
    "price": 23.91,
    "cartonQty": 12,
    "weight": 0.0,
    "initialSupplier": "Nippys",
    "sellByUnit": true,
    "sellByCarton": true,
    "regional": 33.0,
    "archive": false,
    "image": "assets/images/Nippys_Mixed_Juice_450ml.png"
  },
  {
    "id": 293,
    "sku": "",
    "name": "Nippys Apple Juice (Glass) 350ml",
    "description": "",
    "storageLocation": "",
    "category": "Fruit Juice",
    "metro": 0.0,
    "wholesale": 0.0,
    "price": 0.0,
    "cartonQty": 1,
    "weight": 0.0,
    "initialSupplier": "",
    "sellByUnit": true,
    "sellByCarton": false,
    "regional": 0.0,
    "archive": false,
    "image": "assets/images/Nippys_Apple_Juice_(Glass)_350ml.png"
  },
  {
    "id": 294,
    "sku": "NABC350",
    "name": "Nippys Apple Blackcurrant Juice Glass 350ml",
    "description": "",
    "storageLocation": "",
    "category": "Fruit Juice",
    "metro": 34.0,
    "wholesale": 0.0,
    "price": 25.0,
    "cartonQty": 12,
    "weight": 0.0,
    "initialSupplier": "Nippys",
    "sellByUnit": false,
    "sellByCarton": true,
    "regional": 35.4,
    "archive": false,
    "image": "assets/images/Nippys_Apple_Blackcurrant_Juice_Glass_350ml.png"
  },
  {
    "id": 295,
    "sku": "NOJ250",
    "name": "Nippys Orange Juice 250ml",
    "description": "",
    "storageLocation": "",
    "category": "Fruit Juice",
    "metro": 30.0,
    "wholesale": 0.0,
    "price": 23.78,
    "cartonQty": 24,
    "weight": 0.0,
    "initialSupplier": "Nippys",
    "sellByUnit": false,
    "sellByCarton": true,
    "regional": 31.2,
    "archive": false,
    "image": "assets/images/Nippys_Orange_Juice_250ml.png"
  },
  {
    "id": 296,
    "sku": "NAP250",
    "name": "Nippys Apple Juice 250ml",
    "description": "",
    "storageLocation": "",
    "category": "Fruit Juice",
    "metro": 30.0,
    "wholesale": 0.0,
    "price": 23.78,
    "cartonQty": 24,
    "weight": 0.0,
    "initialSupplier": "Nippys",
    "sellByUnit": false,
    "sellByCarton": true,
    "regional": 31.2,
    "archive": false,
    "image": "assets/images/Nippys_Apple_Juice_250ml.png"
  },
  {
    "id": 297,
    "sku": "",
    "name": "Nippys Choc Banana 500ml",
    "description": "",
    "storageLocation": "",
    "category": "Flavoured Milk",
    "metro": 0.0,
    "wholesale": 0.0,
    "price": 0.0,
    "cartonQty": 1,
    "weight": 0.0,
    "initialSupplier": "",
    "sellByUnit": true,
    "sellByCarton": false,
    "regional": 0.0,
    "archive": false,
    "image": "assets/images/Nippys_Choc_Banana_500ml.png"
  },
  {
    "id": 298,
    "sku": "NUNSOJ2L",
    "name": "Nippys Unsweetened Orange Juice 2L",
    "description": "",
    "storageLocation": "",
    "category": "Fruit Juice",
    "metro": 31.2,
    "wholesale": 0.0,
    "price": 27.64,
    "cartonQty": 6,
    "weight": 0.0,
    "initialSupplier": "Nippys",
    "sellByUnit": false,
    "sellByCarton": true,
    "regional": 34.02,
    "archive": false,
    "image": "assets/images/Nippys_Unsweetened_Orange_Juice_2L.png"
  },
  {
    "id": 301,
    "sku": "VBLU350",
    "name": "V Blue (Glass) 350ml",
    "description": "",
    "storageLocation": "",
    "category": "Energy Drink",
    "metro": 72.0,
    "wholesale": 0.0,
    "price": 62.0,
    "cartonQty": 24,
    "weight": 0.0,
    "initialSupplier": "CJM",
    "sellByUnit": false,
    "sellByCarton": true,
    "regional": 76.0,
    "archive": false,
    "image": "assets/images/V_Blue_(Glass)_350ml.png"
  },
  {
    "id": 305,
    "sku": "",
    "name": "Nippys Orange Juice (Glass) 350ml",
    "description": "",
    "storageLocation": "",
    "category": "Fruit Juice",
    "metro": 0.0,
    "wholesale": 0.0,
    "price": 0.0,
    "cartonQty": 1,
    "weight": 0.0,
    "initialSupplier": "",
    "sellByUnit": true,
    "sellByCarton": false,
    "regional": 0.0,
    "archive": false,
    "image": "assets/images/Nippys_Orange_Juice_(Glass)_350ml.png"
  },
  {
    "id": 307,
    "sku": "NPG1L",
    "name": "Nippys Pink Grapefruit Juice 1L",
    "description": "",
    "storageLocation": "",
    "category": "Fruit Juice",
    "metro": 27.0,
    "wholesale": 0.0,
    "price": 20.64,
    "cartonQty": 6,
    "weight": 0.0,
    "initialSupplier": "Nippys",
    "sellByUnit": false,
    "sellByCarton": true,
    "regional": 30.0,
    "archive": false,
    "image": "assets/images/Nippys_Pink_Grapefruit_Juice_1L.png"
  },
  {
    "id": 314,
    "sku": "",
    "name": "V Original 250ml",
    "description": "",
    "storageLocation": "",
    "category": "Energy Drink",
    "metro": 0.0,
    "wholesale": 0.0,
    "price": 0.0,
    "cartonQty": 1,
    "weight": 0.0,
    "initialSupplier": "",
    "sellByUnit": true,
    "sellByCarton": false,
    "regional": 0.0,
    "archive": false,
    "image": "assets/images/V_Original_250ml.png"
  },
  {
    "id": 315,
    "sku": "",
    "name": "V Original 500ml",
    "description": "",
    "storageLocation": "",
    "category": "Energy Drink",
    "metro": 0.0,
    "wholesale": 0.0,
    "price": 0.0,
    "cartonQty": 1,
    "weight": 0.0,
    "initialSupplier": "",
    "sellByUnit": true,
    "sellByCarton": false,
    "regional": 0.0,
    "archive": false,
    "image": "assets/images/V_Original_500ml.png"
  },
  {
    "id": 316,
    "sku": "",
    "name": "V Original (Glass) 350ml",
    "description": "",
    "storageLocation": "",
    "category": "Energy Drink",
    "metro": 0.0,
    "wholesale": 0.0,
    "price": 0.0,
    "cartonQty": 1,
    "weight": 0.0,
    "initialSupplier": "",
    "sellByUnit": true,
    "sellByCarton": false,
    "regional": 0.0,
    "archive": false,
    "image": "assets/images/V_Original_(Glass)_350ml.png"
  },
  {
    "id": 321,
    "sku": "",
    "name": "Nippys Orange & Passionfruit Juice 500ml",
    "description": "",
    "storageLocation": "",
    "category": "Fruit Juice",
    "metro": 0.0,
    "wholesale": 0.0,
    "price": 0.0,
    "cartonQty": 1,
    "weight": 0.0,
    "initialSupplier": "",
    "sellByUnit": true,
    "sellByCarton": false,
    "regional": 0.0,
    "archive": false,
    "image": "assets/images/Nippys_Orange_&_Passionfruit_Juice_500ml.png"
  },
  {
    "id": 322,
    "sku": "",
    "name": "Nippys Apple Blackcurrant Juice 500ml",
    "description": "",
    "storageLocation": "",
    "category": "Fruit Juice",
    "metro": 0.0,
    "wholesale": 0.0,
    "price": 0.0,
    "cartonQty": 1,
    "weight": 0.0,
    "initialSupplier": "",
    "sellByUnit": true,
    "sellByCarton": false,
    "regional": 0.0,
    "archive": false,
    "image": "assets/images/Nippys_Apple_Blackcurrant_Juice_500ml.png"
  },
  {
    "id": 330,
    "sku": "",
    "name": "V Glass 350ml",
    "description": "",
    "storageLocation": "",
    "category": "Energy Drink",
    "metro": 0.0,
    "wholesale": 0.0,
    "price": 0.0,
    "cartonQty": 1,
    "weight": 0.0,
    "initialSupplier": "",
    "sellByUnit": true,
    "sellByCarton": false,
    "regional": 0.0,
    "archive": false,
    "image": "assets/images/V_Glass_350ml.png"
  },
  {
    "id": 332,
    "sku": "",
    "name": "V Blue ( 2 x 12 packs ) 500ml",
    "description": "",
    "storageLocation": "",
    "category": "Energy Drink",
    "metro": 0.0,
    "wholesale": 0.0,
    "price": 0.0,
    "cartonQty": 1,
    "weight": 0.0,
    "initialSupplier": "",
    "sellByUnit": true,
    "sellByCarton": false,
    "regional": 0.0,
    "archive": false,
    "image": "assets/images/V_Blue_(_2_x_12_packs_)_500ml.png"
  },
  {
    "id": 371,
    "sku": "",
    "name": "Maximus Purple 1L",
    "description": "",
    "storageLocation": "",
    "category": "Energy Drink",
    "metro": 0.0,
    "wholesale": 0.0,
    "price": 0.0,
    "cartonQty": 1,
    "weight": 0.0,
    "initialSupplier": "",
    "sellByUnit": true,
    "sellByCarton": false,
    "regional": 0.0,
    "archive": false,
    "image": "assets/images/Maximus_Purple_1L.png"
  },
  {
    "id": 376,
    "sku": "",
    "name": "Danfels Mixed (2 Boxes) 500ml",
    "description": "",
    "storageLocation": "",
    "category": "Unknown",
    "metro": 0.0,
    "wholesale": 0.0,
    "price": 0.0,
    "cartonQty": 1,
    "weight": 0.0,
    "initialSupplier": "",
    "sellByUnit": true,
    "sellByCarton": false,
    "regional": 0.0,
    "archive": false,
    "image": "assets/images/Danfels_Mixed_(2_Boxes)_500ml.png"
  },
  {
    "id": 380,
    "sku": "",
    "name": "V Green Glass 355ml",
    "description": "",
    "storageLocation": "",
    "category": "Energy Drink",
    "metro": 0.0,
    "wholesale": 0.0,
    "price": 0.0,
    "cartonQty": 1,
    "weight": 0.0,
    "initialSupplier": "",
    "sellByUnit": true,
    "sellByCarton": false,
    "regional": 0.0,
    "archive": false,
    "image": "assets/images/V_Green_Glass_355ml.png"
  },
  {
    "id": 381,
    "sku": "",
    "name": "V Blue Glass 355ml",
    "description": "",
    "storageLocation": "",
    "category": "Energy Drink",
    "metro": 0.0,
    "wholesale": 0.0,
    "price": 0.0,
    "cartonQty": 1,
    "weight": 0.0,
    "initialSupplier": "",
    "sellByUnit": true,
    "sellByCarton": false,
    "regional": 0.0,
    "archive": false,
    "image": "assets/images/V_Blue_Glass_355ml.png"
  },
  {
    "id": 383,
    "sku": "DAVW500",
    "name": "Danfels Aloe Vera Watermelon 500ml",
    "description": "",
    "storageLocation": "",
    "category": "Aloe Vera",
    "metro": 1.7,
    "wholesale": 0.0,
    "price": 1.05,
    "cartonQty": 24,
    "weight": 0.0,
    "initialSupplier": "Vinut",
    "sellByUnit": true,
    "sellByCarton": true,
    "regional": 1.8333,
    "archive": false,
    "image": "assets/images/Danfels_Aloe_Vera_Watermelon_500ml.png"
  },
  {
    "id": 384,
    "sku": "DAVM500",
    "name": "Danfels Aloe Vera Mango 500ml",
    "description": "",
    "storageLocation": "",
    "category": "Aloe Vera",
    "metro": 1.7,
    "wholesale": 0.0,
    "price": 1.05,
    "cartonQty": 24,
    "weight": 0.0,
    "initialSupplier": "Vinut",
    "sellByUnit": true,
    "sellByCarton": true,
    "regional": 1.8333,
    "archive": false,
    "image": "assets/images/Danfels_Aloe_Vera_Mango_500ml.png"
  },
  {
    "id": 385,
    "sku": "DAVL500",
    "name": "Danfels Aloe Vera Lychee 500ml",
    "description": "",
    "storageLocation": "",
    "category": "Aloe Vera",
    "metro": 1.7,
    "wholesale": 0.0,
    "price": 1.05,
    "cartonQty": 24,
    "weight": 0.0,
    "initialSupplier": "Vinut",
    "sellByUnit": true,
    "sellByCarton": true,
    "regional": 1.8333,
    "archive": false,
    "image": "assets/images/Danfels_Aloe_Vera_Lychee_500ml.png"
  },
  {
    "id": 386,
    "sku": "DAVO500",
    "name": "Danfels Aloe Vera Original 500ml",
    "description": "",
    "storageLocation": "",
    "category": "Aloe Vera",
    "metro": 1.7,
    "wholesale": 0.0,
    "price": 1.05,
    "cartonQty": 24,
    "weight": 0.0,
    "initialSupplier": "Vinut",
    "sellByUnit": true,
    "sellByCarton": true,
    "regional": 1.8333,
    "archive": false,
    "image": "assets/images/Danfels_Aloe_Vera_Original_500ml.png"
  },
  {
    "id": 387,
    "sku": "DAVP500",
    "name": "Danfels Aloe Vera Peach 500ml",
    "description": "",
    "storageLocation": "",
    "category": "Aloe Vera",
    "metro": 1.7,
    "wholesale": 0.0,
    "price": 1.05,
    "cartonQty": 24,
    "weight": 0.0,
    "initialSupplier": "Vinut",
    "sellByUnit": true,
    "sellByCarton": true,
    "regional": 1.8333,
    "archive": false,
    "image": "assets/images/Danfels_Aloe_Vera_Peach_500ml.png"
  },
  {
    "id": 388,
    "sku": "",
    "name": "Danfels Aloe Vera Mixed (3 cases) 500ml",
    "description": "",
    "storageLocation": "",
    "category": "Aloe Vera",
    "metro": 0.0,
    "wholesale": 0.0,
    "price": 0.0,
    "cartonQty": 1,
    "weight": 0.0,
    "initialSupplier": "",
    "sellByUnit": true,
    "sellByCarton": false,
    "regional": 0.0,
    "archive": false,
    "image": "assets/images/Danfels_Aloe_Vera_Mixed_(3_cases)_500ml.png"
  },
  {
    "id": 402,
    "sku": "",
    "name": "Nippys Apple Juice Glass 350ml",
    "description": "",
    "storageLocation": "",
    "category": "Fruit Juice",
    "metro": 0.0,
    "wholesale": 0.0,
    "price": 0.0,
    "cartonQty": 1,
    "weight": 0.0,
    "initialSupplier": "",
    "sellByUnit": true,
    "sellByCarton": false,
    "regional": 0.0,
    "archive": false,
    "image": "assets/images/Nippys_Apple_Juice_Glass_350ml.png"
  },
  {
    "id": 403,
    "sku": "",
    "name": "Danfels Aloe Vera Mixed  (24 units) 500ml",
    "description": "",
    "storageLocation": "",
    "category": "Aloe Vera",
    "metro": 0.0,
    "wholesale": 0.0,
    "price": 0.0,
    "cartonQty": 1,
    "weight": 0.0,
    "initialSupplier": "",
    "sellByUnit": true,
    "sellByCarton": false,
    "regional": 0.0,
    "archive": false,
    "image": "assets/images/Danfels_Aloe_Vera_Mixed__(24_units)_500ml.png"
  },
  {
    "id": 419,
    "sku": "",
    "name": "Mother Frosty Berry 500ml",
    "description": "",
    "storageLocation": "",
    "category": "Energy Drink",
    "metro": 0.0,
    "wholesale": 0.0,
    "price": 0.0,
    "cartonQty": 1,
    "weight": 0.0,
    "initialSupplier": "",
    "sellByUnit": true,
    "sellByCarton": false,
    "regional": 0.0,
    "archive": false,
    "image": "assets/images/Mother_Frosty_Berry_500ml.png"
  },
  {
    "id": 421,
    "sku": "",
    "name": "Gatorade Blue Bolt 600ml",
    "description": "",
    "storageLocation": "",
    "category": "Energy Drink",
    "metro": 0.0,
    "wholesale": 0.0,
    "price": 0.0,
    "cartonQty": 1,
    "weight": 0.0,
    "initialSupplier": "",
    "sellByUnit": true,
    "sellByCarton": false,
    "regional": 0.0,
    "archive": false,
    "image": "assets/images/Gatorade_Blue_Bolt_600ml.png"
  },
  {
    "id": 422,
    "sku": "",
    "name": "Danfels Aloe Vera Pineapple 500ml",
    "description": "",
    "storageLocation": "",
    "category": "Aloe Vera",
    "metro": 0.0,
    "wholesale": 0.0,
    "price": 0.0,
    "cartonQty": 1,
    "weight": 0.0,
    "initialSupplier": "",
    "sellByUnit": true,
    "sellByCarton": false,
    "regional": 0.0,
    "archive": false,
    "image": "assets/images/Danfels_Aloe_Vera_Pineapple_500ml.png"
  },
  {
    "id": 423,
    "sku": "",
    "name": "Danfels Aloe Vera Pomegranate 500ml",
    "description": "",
    "storageLocation": "",
    "category": "Aloe Vera",
    "metro": 0.0,
    "wholesale": 0.0,
    "price": 0.0,
    "cartonQty": 1,
    "weight": 0.0,
    "initialSupplier": "",
    "sellByUnit": true,
    "sellByCarton": false,
    "regional": 0.0,
    "archive": false,
    "image": "assets/images/Danfels_Aloe_Vera_Pomegranate_500ml.png"
  },
  {
    "id": 430,
    "sku": "",
    "name": "Gatorade Tropical 600ml",
    "description": "",
    "storageLocation": "",
    "category": "Energy Drink",
    "metro": 0.0,
    "wholesale": 0.0,
    "price": 0.0,
    "cartonQty": 1,
    "weight": 0.0,
    "initialSupplier": "",
    "sellByUnit": true,
    "sellByCarton": false,
    "regional": 0.0,
    "archive": false,
    "image": "assets/images/Gatorade_Tropical_600ml.png"
  },
  {
    "id": 436,
    "sku": "",
    "name": "Nippys Strawberry Milk 1L",
    "description": "",
    "storageLocation": "",
    "category": "Unknown",
    "metro": 0.0,
    "wholesale": 0.0,
    "price": 0.0,
    "cartonQty": 1,
    "weight": 0.0,
    "initialSupplier": "",
    "sellByUnit": true,
    "sellByCarton": false,
    "regional": 0.0,
    "archive": false,
    "image": "assets/images/Nippys_Strawberry_Milk_1L.png"
  },
  {
    "id": 442,
    "sku": "",
    "name": "Nippy Strawberry Milk 250ml",
    "description": "",
    "storageLocation": "",
    "category": "Unknown",
    "metro": 0.0,
    "wholesale": 0.0,
    "price": 0.0,
    "cartonQty": 1,
    "weight": 0.0,
    "initialSupplier": "",
    "sellByUnit": true,
    "sellByCarton": false,
    "regional": 0.0,
    "archive": false,
    "image": "assets/images/Nippy_Strawberry_Milk_250ml.png"
  },
  {
    "id": 447,
    "sku": "",
    "name": "Gatorade Grape 600ml",
    "description": "",
    "storageLocation": "",
    "category": "Energy Drink",
    "metro": 0.0,
    "wholesale": 0.0,
    "price": 0.0,
    "cartonQty": 1,
    "weight": 0.0,
    "initialSupplier": "",
    "sellByUnit": true,
    "sellByCarton": false,
    "regional": 0.0,
    "archive": false,
    "image": "assets/images/Gatorade_Grape_600ml.png"
  },
  {
    "id": 448,
    "sku": "",
    "name": "Danfels Aloe Vera Water Mixed 500ml",
    "description": "",
    "storageLocation": "",
    "category": "Aloe Vera",
    "metro": 0.0,
    "wholesale": 0.0,
    "price": 0.0,
    "cartonQty": 1,
    "weight": 0.0,
    "initialSupplier": "",
    "sellByUnit": true,
    "sellByCarton": false,
    "regional": 0.0,
    "archive": false,
    "image": "assets/images/Danfels_Aloe_Vera_Water_Mixed_500ml.png"
  },
  {
    "id": 449,
    "sku": "",
    "name": "Nippys Vanilla Milk (24 pack) 375ml",
    "description": "",
    "storageLocation": "",
    "category": "Unknown",
    "metro": 0.0,
    "wholesale": 0.0,
    "price": 0.0,
    "cartonQty": 1,
    "weight": 0.0,
    "initialSupplier": "",
    "sellByUnit": true,
    "sellByCarton": false,
    "regional": 0.0,
    "archive": false,
    "image": "assets/images/Nippys_Vanilla_Milk_(24_pack)_375ml.png"
  },
  {
    "id": 452,
    "sku": "",
    "name": "Fanta 600ml",
    "description": "",
    "storageLocation": "",
    "category": "Soft Drink",
    "metro": 0.0,
    "wholesale": 0.0,
    "price": 0.0,
    "cartonQty": 1,
    "weight": 0.0,
    "initialSupplier": "",
    "sellByUnit": true,
    "sellByCarton": false,
    "regional": 0.0,
    "archive": false,
    "image": "assets/images/Fanta_600ml.png"
  },
  {
    "id": 453,
    "sku": "",
    "name": "Sprite 600ml",
    "description": "",
    "storageLocation": "",
    "category": "Soft Drink",
    "metro": 0.0,
    "wholesale": 0.0,
    "price": 0.0,
    "cartonQty": 1,
    "weight": 0.0,
    "initialSupplier": "",
    "sellByUnit": true,
    "sellByCarton": false,
    "regional": 0.0,
    "archive": false,
    "image": "assets/images/Sprite_600ml.png"
  },
  {
    "id": 454,
    "sku": "",
    "name": "Nippys Vanilla Milk 600ml",
    "description": "",
    "storageLocation": "",
    "category": "Unknown",
    "metro": 0.0,
    "wholesale": 0.0,
    "price": 0.0,
    "cartonQty": 1,
    "weight": 0.0,
    "initialSupplier": "",
    "sellByUnit": true,
    "sellByCarton": false,
    "regional": 0.0,
    "archive": false,
    "image": "assets/images/Nippys_Vanilla_Milk_600ml.png"
  },
  {
    "id": 455,
    "sku": "",
    "name": "Raspberry Fanta 600ml",
    "description": "",
    "storageLocation": "",
    "category": "Soft Drink",
    "metro": 0.0,
    "wholesale": 0.0,
    "price": 0.0,
    "cartonQty": 1,
    "weight": 0.0,
    "initialSupplier": "",
    "sellByUnit": true,
    "sellByCarton": false,
    "regional": 0.0,
    "archive": false,
    "image": "assets/images/Raspberry_Fanta_600ml.png"
  },
  {
    "id": 458,
    "sku": "",
    "name": "Coke No Sugar 600ml",
    "description": "",
    "storageLocation": "",
    "category": "Soft Drink",
    "metro": 0.0,
    "wholesale": 0.0,
    "price": 0.0,
    "cartonQty": 1,
    "weight": 0.0,
    "initialSupplier": "",
    "sellByUnit": true,
    "sellByCarton": false,
    "regional": 0.0,
    "archive": false,
    "image": "assets/images/Coke_No_Sugar_600ml.png"
  },
  {
    "id": 460,
    "sku": "",
    "name": "Bundaberg Ginger Beer (24 pack)",
    "description": "",
    "storageLocation": "",
    "category": "Soft Drink",
    "metro": 0.0,
    "wholesale": 0.0,
    "price": 0.0,
    "cartonQty": 1,
    "weight": 0.0,
    "initialSupplier": "",
    "sellByUnit": true,
    "sellByCarton": false,
    "regional": 0.0,
    "archive": false,
    "image": "assets/images/Bundaberg_Ginger_Beer_(24_pack).png"
  },
  {
    "id": 461,
    "sku": "",
    "name": "Bundaberg Ginger Beer Diet (12 pack)",
    "description": "",
    "storageLocation": "",
    "category": "Soft Drink",
    "metro": 0.0,
    "wholesale": 0.0,
    "price": 0.0,
    "cartonQty": 1,
    "weight": 0.0,
    "initialSupplier": "",
    "sellByUnit": true,
    "sellByCarton": false,
    "regional": 0.0,
    "archive": false,
    "image": "assets/images/Bundaberg_Ginger_Beer_Diet_(12_pack).png"
  },
  {
    "id": 470,
    "sku": "",
    "name": "Lipton Mango 500ml",
    "description": "",
    "storageLocation": "",
    "category": "Iced Tea",
    "metro": 0.0,
    "wholesale": 0.0,
    "price": 0.0,
    "cartonQty": 1,
    "weight": 0.0,
    "initialSupplier": "",
    "sellByUnit": true,
    "sellByCarton": false,
    "regional": 0.0,
    "archive": false,
    "image": "assets/images/Lipton_Mango_500ml.png"
  },
  {
    "id": 471,
    "sku": "",
    "name": "Multi 350ml",
    "description": "",
    "storageLocation": "",
    "category": "Unknown",
    "metro": 0.0,
    "wholesale": 0.0,
    "price": 0.0,
    "cartonQty": 1,
    "weight": 0.0,
    "initialSupplier": "",
    "sellByUnit": true,
    "sellByCarton": false,
    "regional": 0.0,
    "archive": false,
    "image": "assets/images/Multi_350ml.png"
  },
  {
    "id": 472,
    "sku": "",
    "name": "Apple Mango Banana Juice 350ml",
    "description": "",
    "storageLocation": "",
    "category": "Fruit Juice",
    "metro": 0.0,
    "wholesale": 0.0,
    "price": 0.0,
    "cartonQty": 1,
    "weight": 0.0,
    "initialSupplier": "",
    "sellByUnit": true,
    "sellByCarton": false,
    "regional": 0.0,
    "archive": false,
    "image": "assets/images/Apple_Mango_Banana_Juice_350ml.png"
  },
  {
    "id": 473,
    "sku": "",
    "name": "Nippys Orange Juice 3L",
    "description": "",
    "storageLocation": "",
    "category": "Fruit Juice",
    "metro": 0.0,
    "wholesale": 0.0,
    "price": 0.0,
    "cartonQty": 1,
    "weight": 0.0,
    "initialSupplier": "",
    "sellByUnit": true,
    "sellByCarton": false,
    "regional": 0.0,
    "archive": false,
    "image": "assets/images/Nippys_Orange_Juice_3L.png"
  },
  {
    "id": 474,
    "sku": "",
    "name": "Tropical 2L",
    "description": "",
    "storageLocation": "",
    "category": "Fruit Juice",
    "metro": 0.0,
    "wholesale": 0.0,
    "price": 0.0,
    "cartonQty": 1,
    "weight": 0.0,
    "initialSupplier": "",
    "sellByUnit": true,
    "sellByCarton": false,
    "regional": 0.0,
    "archive": false,
    "image": "assets/images/Tropical_2L.png"
  },
  {
    "id": 478,
    "sku": "",
    "name": "Apple Guava Juice 350ml",
    "description": "",
    "storageLocation": "",
    "category": "Fruit Juice",
    "metro": 0.0,
    "wholesale": 0.0,
    "price": 0.0,
    "cartonQty": 1,
    "weight": 0.0,
    "initialSupplier": "",
    "sellByUnit": true,
    "sellByCarton": false,
    "regional": 0.0,
    "archive": false,
    "image": "assets/images/Apple_Guava_Juice_350ml.png"
  },
  {
    "id": 479,
    "sku": "",
    "name": "Nippys Pineapple Juice 350ml",
    "description": "",
    "storageLocation": "",
    "category": "Fruit Juice",
    "metro": 0.0,
    "wholesale": 0.0,
    "price": 0.0,
    "cartonQty": 1,
    "weight": 0.0,
    "initialSupplier": "",
    "sellByUnit": true,
    "sellByCarton": false,
    "regional": 0.0,
    "archive": false,
    "image": "assets/images/Nippys_Pineapple_Juice_350ml.png"
  },
  {
    "id": 480,
    "sku": "",
    "name": "Lipton Lemon 500ml",
    "description": "",
    "storageLocation": "",
    "category": "Iced Tea",
    "metro": 0.0,
    "wholesale": 0.0,
    "price": 0.0,
    "cartonQty": 1,
    "weight": 0.0,
    "initialSupplier": "",
    "sellByUnit": true,
    "sellByCarton": false,
    "regional": 0.0,
    "archive": false,
    "image": "assets/images/Lipton_Lemon_500ml.png"
  },
  {
    "id": 481,
    "sku": "",
    "name": "Lipton Peach 500ml",
    "description": "",
    "storageLocation": "",
    "category": "Iced Tea",
    "metro": 0.0,
    "wholesale": 0.0,
    "price": 0.0,
    "cartonQty": 1,
    "weight": 0.0,
    "initialSupplier": "",
    "sellByUnit": true,
    "sellByCarton": false,
    "regional": 0.0,
    "archive": false,
    "image": "assets/images/Lipton_Peach_500ml.png"
  },
  {
    "id": 484,
    "sku": "",
    "name": "Lipton Raspberry 500ml",
    "description": "",
    "storageLocation": "",
    "category": "Iced Tea",
    "metro": 0.0,
    "wholesale": 0.0,
    "price": 0.0,
    "cartonQty": 1,
    "weight": 0.0,
    "initialSupplier": "",
    "sellByUnit": true,
    "sellByCarton": false,
    "regional": 0.0,
    "archive": false,
    "image": "assets/images/Lipton_Raspberry_500ml.png"
  },
  {
    "id": 485,
    "sku": "",
    "name": "Mineral Water Plain 600ml",
    "description": "",
    "storageLocation": "",
    "category": "Mineral Water",
    "metro": 0.0,
    "wholesale": 0.0,
    "price": 0.0,
    "cartonQty": 1,
    "weight": 0.0,
    "initialSupplier": "",
    "sellByUnit": true,
    "sellByCarton": false,
    "regional": 0.0,
    "archive": false,
    "image": "assets/images/Mineral_Water_Plain_600ml.png"
  },
  {
    "id": 486,
    "sku": "",
    "name": "Apple & Ginger Juice 1L",
    "description": "",
    "storageLocation": "",
    "category": "Fruit Juice",
    "metro": 0.0,
    "wholesale": 0.0,
    "price": 0.0,
    "cartonQty": 1,
    "weight": 0.0,
    "initialSupplier": "",
    "sellByUnit": true,
    "sellByCarton": false,
    "regional": 0.0,
    "archive": false,
    "image": "assets/images/Apple_&_Ginger_Juice_1L.png"
  },
  {
    "id": 489,
    "sku": "",
    "name": "V Bottles 350ml",
    "description": "",
    "storageLocation": "",
    "category": "Energy Drink",
    "metro": 0.0,
    "wholesale": 0.0,
    "price": 0.0,
    "cartonQty": 1,
    "weight": 0.0,
    "initialSupplier": "",
    "sellByUnit": true,
    "sellByCarton": false,
    "regional": 0.0,
    "archive": false,
    "image": "assets/images/V_Bottles_350ml.png"
  },
  {
    "id": 492,
    "sku": "",
    "name": "Frozen Lemon Juice 2L",
    "description": "",
    "storageLocation": "",
    "category": "Fruit Juice",
    "metro": 0.0,
    "wholesale": 0.0,
    "price": 0.0,
    "cartonQty": 1,
    "weight": 0.0,
    "initialSupplier": "",
    "sellByUnit": true,
    "sellByCarton": false,
    "regional": 0.0,
    "archive": false,
    "image": "assets/images/Frozen_Lemon_Juice_2L.png"
  },
  {
    "id": 494,
    "sku": "",
    "name": "Mineral Water Raspberry Apple 600ml",
    "description": "",
    "storageLocation": "",
    "category": "Mineral Water",
    "metro": 0.0,
    "wholesale": 0.0,
    "price": 0.0,
    "cartonQty": 1,
    "weight": 0.0,
    "initialSupplier": "",
    "sellByUnit": true,
    "sellByCarton": false,
    "regional": 0.0,
    "archive": false,
    "image": "assets/images/Mineral_Water_Raspberry_Apple_600ml.png"
  },
  {
    "id": 498,
    "sku": "",
    "name": "Gatorade Orange 600ml",
    "description": "",
    "storageLocation": "",
    "category": "Energy Drink",
    "metro": 0.0,
    "wholesale": 0.0,
    "price": 0.0,
    "cartonQty": 1,
    "weight": 0.0,
    "initialSupplier": "",
    "sellByUnit": true,
    "sellByCarton": false,
    "regional": 0.0,
    "archive": false,
    "image": "assets/images/Gatorade_Orange_600ml.png"
  },
  {
    "id": 499,
    "sku": "",
    "name": "Gatorade Lemon Lime 600ml",
    "description": "",
    "storageLocation": "",
    "category": "Energy Drink",
    "metro": 0.0,
    "wholesale": 0.0,
    "price": 0.0,
    "cartonQty": 1,
    "weight": 0.0,
    "initialSupplier": "",
    "sellByUnit": true,
    "sellByCarton": false,
    "regional": 0.0,
    "archive": false,
    "image": "assets/images/Gatorade_Lemon_Lime_600ml.png"
  },
  {
    "id": 501,
    "sku": "",
    "name": "Mineral Water Sparkling 600ml",
    "description": "",
    "storageLocation": "",
    "category": "Mineral Water",
    "metro": 0.0,
    "wholesale": 0.0,
    "price": 0.0,
    "cartonQty": 1,
    "weight": 0.0,
    "initialSupplier": "",
    "sellByUnit": true,
    "sellByCarton": false,
    "regional": 0.0,
    "archive": false,
    "image": "assets/images/Mineral_Water_Sparkling_600ml.png"
  },
  {
    "id": 502,
    "sku": "",
    "name": "Danfels Aloe Vera Original 1.5L",
    "description": "",
    "storageLocation": "",
    "category": "Aloe Vera",
    "metro": 0.0,
    "wholesale": 0.0,
    "price": 0.0,
    "cartonQty": 1,
    "weight": 0.0,
    "initialSupplier": "",
    "sellByUnit": true,
    "sellByCarton": false,
    "regional": 0.0,
    "archive": false,
    "image": "assets/images/Danfels_Aloe_Vera_Original_1.5L.png"
  },
  {
    "id": 508,
    "sku": "",
    "name": "ABC 350ml",
    "description": "",
    "storageLocation": "",
    "category": "Fruit Juice",
    "metro": 0.0,
    "wholesale": 0.0,
    "price": 0.0,
    "cartonQty": 1,
    "weight": 0.0,
    "initialSupplier": "",
    "sellByUnit": true,
    "sellByCarton": false,
    "regional": 0.0,
    "archive": false,
    "image": "assets/images/ABC_350ml.png"
  },
  {
    "id": 509,
    "sku": "",
    "name": "AMB 350ml",
    "description": "",
    "storageLocation": "",
    "category": "Fruit Juice",
    "metro": 0.0,
    "wholesale": 0.0,
    "price": 0.0,
    "cartonQty": 1,
    "weight": 0.0,
    "initialSupplier": "",
    "sellByUnit": true,
    "sellByCarton": false,
    "regional": 0.0,
    "archive": false,
    "image": "assets/images/AMB_350ml.png"
  },
  {
    "id": 510,
    "sku": "",
    "name": "Diet Coke 600ml",
    "description": "",
    "storageLocation": "",
    "category": "Soft Drink",
    "metro": 0.0,
    "wholesale": 0.0,
    "price": 0.0,
    "cartonQty": 1,
    "weight": 0.0,
    "initialSupplier": "",
    "sellByUnit": true,
    "sellByCarton": false,
    "regional": 0.0,
    "archive": false,
    "image": "assets/images/Diet_Coke_600ml.png"
  },
  {
    "id": 511,
    "sku": "",
    "name": "Sprite No Sugar 600ml",
    "description": "",
    "storageLocation": "",
    "category": "Soft Drink",
    "metro": 0.0,
    "wholesale": 0.0,
    "price": 0.0,
    "cartonQty": 1,
    "weight": 0.0,
    "initialSupplier": "",
    "sellByUnit": true,
    "sellByCarton": false,
    "regional": 0.0,
    "archive": false,
    "image": "assets/images/Sprite_No_Sugar_600ml.png"
  },
  {
    "id": 513,
    "sku": "",
    "name": "Juice Mixed Boxes 450ml",
    "description": "",
    "storageLocation": "",
    "category": "Fruit Juice",
    "metro": 0.0,
    "wholesale": 0.0,
    "price": 0.0,
    "cartonQty": 1,
    "weight": 0.0,
    "initialSupplier": "",
    "sellByUnit": true,
    "sellByCarton": false,
    "regional": 0.0,
    "archive": false,
    "image": "assets/images/Juice_Mixed_Boxes_450ml.png"
  },
  {
    "id": 515,
    "sku": "",
    "name": "Apple Orange Carrot Juice 1L",
    "description": "",
    "storageLocation": "",
    "category": "Fruit Juice",
    "metro": 0.0,
    "wholesale": 0.0,
    "price": 0.0,
    "cartonQty": 1,
    "weight": 0.0,
    "initialSupplier": "",
    "sellByUnit": true,
    "sellByCarton": false,
    "regional": 0.0,
    "archive": false,
    "image": "assets/images/Apple_Orange_Carrot_Juice_1L.png"
  },
  {
    "id": 516,
    "sku": "",
    "name": "Mineral Water Lemon Lime 600ml",
    "description": "",
    "storageLocation": "",
    "category": "Mineral Water",
    "metro": 0.0,
    "wholesale": 0.0,
    "price": 0.0,
    "cartonQty": 1,
    "weight": 0.0,
    "initialSupplier": "",
    "sellByUnit": true,
    "sellByCarton": false,
    "regional": 0.0,
    "archive": false,
    "image": "assets/images/Mineral_Water_Lemon_Lime_600ml.png"
  },
  {
    "id": 517,
    "sku": "",
    "name": "Mineral Water Natural 600ml",
    "description": "",
    "storageLocation": "",
    "category": "Water",
    "metro": 0.0,
    "wholesale": 0.0,
    "price": 0.0,
    "cartonQty": 1,
    "weight": 0.0,
    "initialSupplier": "",
    "sellByUnit": true,
    "sellByCarton": false,
    "regional": 0.0,
    "archive": false,
    "image": "assets/images/Mineral_Water_Natural_600ml.png"
  },
  {
    "id": 518,
    "sku": "",
    "name": "Sprite Lemon 600ml",
    "description": "",
    "storageLocation": "",
    "category": "Soft Drink",
    "metro": 0.0,
    "wholesale": 0.0,
    "price": 0.0,
    "cartonQty": 1,
    "weight": 0.0,
    "initialSupplier": "",
    "sellByUnit": true,
    "sellByCarton": false,
    "regional": 0.0,
    "archive": false,
    "image": "assets/images/Sprite_Lemon_600ml.png"
  },
  {
    "id": 519,
    "sku": "",
    "name": "Ginger Beer (12 pack) 375ml",
    "description": "",
    "storageLocation": "",
    "category": "Soft Drink",
    "metro": 0.0,
    "wholesale": 0.0,
    "price": 0.0,
    "cartonQty": 1,
    "weight": 0.0,
    "initialSupplier": "",
    "sellByUnit": true,
    "sellByCarton": false,
    "regional": 0.0,
    "archive": false,
    "image": "assets/images/Ginger_Beer_(12_pack)_375ml.png"
  },
  {
    "id": 522,
    "sku": "",
    "name": "Danfels Aloe Vera Mixed - 6 Flavours x 4 each 500ml",
    "description": "",
    "storageLocation": "",
    "category": "Aloe Vera",
    "metro": 0.0,
    "wholesale": 0.0,
    "price": 0.0,
    "cartonQty": 1,
    "weight": 0.0,
    "initialSupplier": "",
    "sellByUnit": true,
    "sellByCarton": false,
    "regional": 0.0,
    "archive": false,
    "image": "assets/images/Danfels_Aloe_Vera_Mixed_-_6_Flavours_x_4_each_500ml.png"
  },
  {
    "id": 524,
    "sku": "",
    "name": "Greentime Peach 490ml",
    "description": "",
    "storageLocation": "",
    "category": "Coconut Water",
    "metro": 0.0,
    "wholesale": 0.0,
    "price": 0.0,
    "cartonQty": 1,
    "weight": 0.0,
    "initialSupplier": "",
    "sellByUnit": true,
    "sellByCarton": false,
    "regional": 0.0,
    "archive": false,
    "image": "assets/images/Greentime_Peach_490ml.png"
  },
  {
    "id": 527,
    "sku": "",
    "name": "Tangy Lemon 2L",
    "description": "",
    "storageLocation": "",
    "category": "Fruit Juice",
    "metro": 0.0,
    "wholesale": 0.0,
    "price": 0.0,
    "cartonQty": 1,
    "weight": 0.0,
    "initialSupplier": "",
    "sellByUnit": true,
    "sellByCarton": false,
    "regional": 0.0,
    "archive": false,
    "image": "assets/images/Tangy_Lemon_2L.png"
  },
  {
    "id": 529,
    "sku": "",
    "name": "Lipton Passionfruit 500ml",
    "description": "",
    "storageLocation": "",
    "category": "Iced Tea",
    "metro": 0.0,
    "wholesale": 0.0,
    "price": 0.0,
    "cartonQty": 1,
    "weight": 0.0,
    "initialSupplier": "",
    "sellByUnit": true,
    "sellByCarton": false,
    "regional": 0.0,
    "archive": false,
    "image": "assets/images/Lipton_Passionfruit_500ml.png"
  },
  {
    "id": 530,
    "sku": "",
    "name": "Mixed Juice 2L",
    "description": "",
    "storageLocation": "",
    "category": "Fruit Juice",
    "metro": 0.0,
    "wholesale": 0.0,
    "price": 0.0,
    "cartonQty": 1,
    "weight": 0.0,
    "initialSupplier": "",
    "sellByUnit": true,
    "sellByCarton": false,
    "regional": 0.0,
    "archive": false,
    "image": "assets/images/Mixed_Juice_2L.png"
  },
  {
    "id": 531,
    "sku": "",
    "name": "Fresh Lemon Juice",
    "description": "",
    "storageLocation": "",
    "category": "Fruit Juice",
    "metro": 0.0,
    "wholesale": 0.0,
    "price": 0.0,
    "cartonQty": 1,
    "weight": 0.0,
    "initialSupplier": "",
    "sellByUnit": true,
    "sellByCarton": false,
    "regional": 0.0,
    "archive": false,
    "image": "assets/images/Fresh_Lemon_Juice.png"
  },
  {
    "id": 534,
    "sku": "",
    "name": "Lipton Peach (24 Pack) 500ml",
    "description": "",
    "storageLocation": "",
    "category": "Iced Tea",
    "metro": 0.0,
    "wholesale": 0.0,
    "price": 0.0,
    "cartonQty": 1,
    "weight": 0.0,
    "initialSupplier": "",
    "sellByUnit": true,
    "sellByCarton": false,
    "regional": 0.0,
    "archive": false,
    "image": "assets/images/Lipton_Peach_(24_Pack)_500ml.png"
  },
  {
    "id": 536,
    "sku": "",
    "name": "Lipton Lemon (24 Pack) 500ml",
    "description": "",
    "storageLocation": "",
    "category": "Iced Tea",
    "metro": 0.0,
    "wholesale": 0.0,
    "price": 0.0,
    "cartonQty": 1,
    "weight": 0.0,
    "initialSupplier": "",
    "sellByUnit": true,
    "sellByCarton": false,
    "regional": 0.0,
    "archive": false,
    "image": "assets/images/Lipton_Lemon_(24_Pack)_500ml.png"
  },
  {
    "id": 537,
    "sku": "",
    "name": "Gatorade Green 600ml",
    "description": "",
    "storageLocation": "",
    "category": "Energy Drink",
    "metro": 0.0,
    "wholesale": 0.0,
    "price": 0.0,
    "cartonQty": 1,
    "weight": 0.0,
    "initialSupplier": "",
    "sellByUnit": true,
    "sellByCarton": false,
    "regional": 0.0,
    "archive": false,
    "image": "assets/images/Gatorade_Green_600ml.png"
  },
  {
    "id": 538,
    "sku": "",
    "name": "Gatorade Green Apple 600ml",
    "description": "",
    "storageLocation": "",
    "category": "Energy Drink",
    "metro": 0.0,
    "wholesale": 0.0,
    "price": 0.0,
    "cartonQty": 1,
    "weight": 0.0,
    "initialSupplier": "",
    "sellByUnit": true,
    "sellByCarton": false,
    "regional": 0.0,
    "archive": false,
    "image": "assets/images/Gatorade_Green_Apple_600ml.png"
  },
  {
    "id": 540,
    "sku": "",
    "name": "Gatorade Watermelon 600ml",
    "description": "",
    "storageLocation": "",
    "category": "Energy Drink",
    "metro": 0.0,
    "wholesale": 0.0,
    "price": 0.0,
    "cartonQty": 1,
    "weight": 0.0,
    "initialSupplier": "",
    "sellByUnit": true,
    "sellByCarton": false,
    "regional": 0.0,
    "archive": false,
    "image": "assets/images/Gatorade_Watermelon_600ml.png"
  },
  {
    "id": 541,
    "sku": "",
    "name": "Monster Mango 500ml",
    "description": "",
    "storageLocation": "",
    "category": "Energy Drink",
    "metro": 0.0,
    "wholesale": 0.0,
    "price": 0.0,
    "cartonQty": 1,
    "weight": 0.0,
    "initialSupplier": "",
    "sellByUnit": true,
    "sellByCarton": false,
    "regional": 0.0,
    "archive": false,
    "image": "assets/images/Monster_Mango_500ml.png"
  },
  {
    "id": 542,
    "sku": "",
    "name": "Ginger Beer (24 pack) 375ml",
    "description": "",
    "storageLocation": "",
    "category": "Soft Drink",
    "metro": 0.0,
    "wholesale": 0.0,
    "price": 0.0,
    "cartonQty": 1,
    "weight": 0.0,
    "initialSupplier": "",
    "sellByUnit": true,
    "sellByCarton": false,
    "regional": 0.0,
    "archive": false,
    "image": "assets/images/Ginger_Beer_(24_pack)_375ml.png"
  },
  {
    "id": 543,
    "sku": "",
    "name": "Ginger Beer Diet (12 pack) 375ml",
    "description": "",
    "storageLocation": "",
    "category": "Soft Drink",
    "metro": 0.0,
    "wholesale": 0.0,
    "price": 0.0,
    "cartonQty": 1,
    "weight": 0.0,
    "initialSupplier": "",
    "sellByUnit": true,
    "sellByCarton": false,
    "regional": 0.0,
    "archive": false,
    "image": "assets/images/Ginger_Beer_Diet_(12_pack)_375ml.png"
  },
  {
    "id": 544,
    "sku": "",
    "name": "Saigon Brew Latte 250ml",
    "description": "",
    "storageLocation": "",
    "category": "Flavoured Milk",
    "metro": 0.0,
    "wholesale": 0.0,
    "price": 0.0,
    "cartonQty": 1,
    "weight": 0.0,
    "initialSupplier": "",
    "sellByUnit": true,
    "sellByCarton": false,
    "regional": 0.0,
    "archive": false,
    "image": "assets/images/Saigon_Brew_Latte_250ml.png"
  },
  {
    "id": 545,
    "sku": "",
    "name": "Bundaberg Lemonade",
    "description": "",
    "storageLocation": "",
    "category": "Soft Drink",
    "metro": 0.0,
    "wholesale": 0.0,
    "price": 0.0,
    "cartonQty": 1,
    "weight": 0.0,
    "initialSupplier": "",
    "sellByUnit": true,
    "sellByCarton": false,
    "regional": 0.0,
    "archive": false,
    "image": "assets/images/Bundaberg_Lemonade.png"
  },
  {
    "id": 546,
    "sku": "",
    "name": "Rockstar Guava 500ml",
    "description": "",
    "storageLocation": "",
    "category": "Unknown",
    "metro": 0.0,
    "wholesale": 0.0,
    "price": 0.0,
    "cartonQty": 1,
    "weight": 0.0,
    "initialSupplier": "",
    "sellByUnit": true,
    "sellByCarton": false,
    "regional": 0.0,
    "archive": false,
    "image": "assets/images/Rockstar_Guava_500ml.png"
  },
  {
    "id": 547,
    "sku": "",
    "name": "Danfels Aloe Vera Lychee (exchange) 500ml",
    "description": "",
    "storageLocation": "",
    "category": "Aloe Vera",
    "metro": 0.0,
    "wholesale": 0.0,
    "price": 0.0,
    "cartonQty": 1,
    "weight": 0.0,
    "initialSupplier": "",
    "sellByUnit": true,
    "sellByCarton": false,
    "regional": 0.0,
    "archive": false,
    "image": "assets/images/Danfels_Aloe_Vera_Lychee_(exchange)_500ml.png"
  },
  {
    "id": 548,
    "sku": "",
    "name": "Saigon Brew Coffee 250ml",
    "description": "",
    "storageLocation": "",
    "category": "Flavoured Milk",
    "metro": 0.0,
    "wholesale": 0.0,
    "price": 0.0,
    "cartonQty": 1,
    "weight": 0.0,
    "initialSupplier": "",
    "sellByUnit": true,
    "sellByCarton": false,
    "regional": 0.0,
    "archive": false,
    "image": "assets/images/Saigon_Brew_Coffee_250ml.png"
  },
  {
    "id": 549,
    "sku": "",
    "name": "Frozen Lemon Juice ( Box of 6) 2L",
    "description": "",
    "storageLocation": "",
    "category": "Fruit Juice",
    "metro": 0.0,
    "wholesale": 0.0,
    "price": 0.0,
    "cartonQty": 1,
    "weight": 0.0,
    "initialSupplier": "",
    "sellByUnit": true,
    "sellByCarton": false,
    "regional": 0.0,
    "archive": false,
    "image": "assets/images/Frozen_Lemon_Juice_(_Box_of_6)_2L.png"
  },
  {
    "id": 550,
    "sku": "",
    "name": "V Glass Original 350ml",
    "description": "",
    "storageLocation": "",
    "category": "Energy Drink",
    "metro": 0.0,
    "wholesale": 0.0,
    "price": 0.0,
    "cartonQty": 1,
    "weight": 0.0,
    "initialSupplier": "",
    "sellByUnit": true,
    "sellByCarton": false,
    "regional": 0.0,
    "archive": false,
    "image": "assets/images/V_Glass_Original_350ml.png"
  },
  {
    "id": 551,
    "sku": "",
    "name": "V Original Sugar Free 250ml",
    "description": "",
    "storageLocation": "",
    "category": "Energy Drink",
    "metro": 0.0,
    "wholesale": 0.0,
    "price": 0.0,
    "cartonQty": 1,
    "weight": 0.0,
    "initialSupplier": "",
    "sellByUnit": true,
    "sellByCarton": false,
    "regional": 0.0,
    "archive": false,
    "image": "assets/images/V_Original_Sugar_Free_250ml.png"
  },
  {
    "id": 552,
    "sku": "",
    "name": "Gatorade Blue Bolt (swap) 600ml",
    "description": "",
    "storageLocation": "",
    "category": "Energy Drink",
    "metro": 0.0,
    "wholesale": 0.0,
    "price": 0.0,
    "cartonQty": 1,
    "weight": 0.0,
    "initialSupplier": "",
    "sellByUnit": true,
    "sellByCarton": false,
    "regional": 0.0,
    "archive": false,
    "image": "assets/images/Gatorade_Blue_Bolt_(swap)_600ml.png"
  },
  {
    "id": 560,
    "sku": "",
    "name": "Mineral Water Paradie Punch 600ml",
    "description": "",
    "storageLocation": "",
    "category": "Mineral Water",
    "metro": 0.0,
    "wholesale": 0.0,
    "price": 0.0,
    "cartonQty": 1,
    "weight": 0.0,
    "initialSupplier": "",
    "sellByUnit": true,
    "sellByCarton": false,
    "regional": 0.0,
    "archive": false,
    "image": "assets/images/Mineral_Water_Paradie_Punch_600ml.png"
  },
  {
    "id": 561,
    "sku": "",
    "name": "Nippys Coffee (24 pack) 375ml",
    "description": "",
    "storageLocation": "",
    "category": "Flavoured Milk",
    "metro": 0.0,
    "wholesale": 0.0,
    "price": 0.0,
    "cartonQty": 1,
    "weight": 0.0,
    "initialSupplier": "",
    "sellByUnit": true,
    "sellByCarton": false,
    "regional": 0.0,
    "archive": false,
    "image": "assets/images/Nippys_Coffee_(24_pack)_375ml.png"
  },
  {
    "id": 562,
    "sku": "",
    "name": "Strawberry Milk 375ml",
    "description": "",
    "storageLocation": "",
    "category": "Unknown",
    "metro": 0.0,
    "wholesale": 0.0,
    "price": 0.0,
    "cartonQty": 1,
    "weight": 0.0,
    "initialSupplier": "",
    "sellByUnit": true,
    "sellByCarton": false,
    "regional": 0.0,
    "archive": false,
    "image": "assets/images/Strawberry_Milk_375ml.png"
  },
  {
    "id": 566,
    "sku": "",
    "name": "Apple Juice Cup (96 units) 110ml",
    "description": "",
    "storageLocation": "",
    "category": "Fruit Juice",
    "metro": 0.0,
    "wholesale": 0.0,
    "price": 0.0,
    "cartonQty": 1,
    "weight": 0.0,
    "initialSupplier": "",
    "sellByUnit": true,
    "sellByCarton": false,
    "regional": 0.0,
    "archive": false,
    "image": "assets/images/Apple_Juice_Cup_(96_units)_110ml.png"
  },
  {
    "id": 567,
    "sku": "",
    "name": "Orange Juice Cup (96 units) 110ml",
    "description": "",
    "storageLocation": "",
    "category": "Fruit Juice",
    "metro": 0.0,
    "wholesale": 0.0,
    "price": 0.0,
    "cartonQty": 1,
    "weight": 0.0,
    "initialSupplier": "",
    "sellByUnit": true,
    "sellByCarton": false,
    "regional": 0.0,
    "archive": false,
    "image": "assets/images/Orange_Juice_Cup_(96_units)_110ml.png"
  },
  {
    "id": 571,
    "sku": "",
    "name": "Nippys Apple Blackcurrant Juice 350ml",
    "description": "",
    "storageLocation": "",
    "category": "Fruit Juice",
    "metro": 0.0,
    "wholesale": 0.0,
    "price": 0.0,
    "cartonQty": 1,
    "weight": 0.0,
    "initialSupplier": "",
    "sellByUnit": true,
    "sellByCarton": false,
    "regional": 0.0,
    "archive": false,
    "image": "assets/images/Nippys_Apple_Blackcurrant_Juice_350ml.png"
  },
  {
    "id": 572,
    "sku": "",
    "name": "Monster Frosty Berry 500ml",
    "description": "",
    "storageLocation": "",
    "category": "Energy Drink",
    "metro": 0.0,
    "wholesale": 0.0,
    "price": 0.0,
    "cartonQty": 1,
    "weight": 0.0,
    "initialSupplier": "",
    "sellByUnit": true,
    "sellByCarton": false,
    "regional": 0.0,
    "archive": false,
    "image": "assets/images/Monster_Frosty_Berry_500ml.png"
  },
  {
    "id": 574,
    "sku": "",
    "name": "Nippys Apple Blackcurrant Juice 250ml",
    "description": "",
    "storageLocation": "",
    "category": "Fruit Juice",
    "metro": 0.0,
    "wholesale": 0.0,
    "price": 0.0,
    "cartonQty": 1,
    "weight": 0.0,
    "initialSupplier": "",
    "sellByUnit": true,
    "sellByCarton": false,
    "regional": 0.0,
    "archive": false,
    "image": "assets/images/Nippys_Apple_Blackcurrant_Juice_250ml.png"
  },
  {
    "id": 586,
    "sku": "",
    "name": "Danfels Aloe Vera Mixed Vinut  x 3 cases",
    "description": "",
    "storageLocation": "",
    "category": "Aloe Vera",
    "metro": 0.0,
    "wholesale": 0.0,
    "price": 0.0,
    "cartonQty": 1,
    "weight": 0.0,
    "initialSupplier": "",
    "sellByUnit": true,
    "sellByCarton": false,
    "regional": 0.0,
    "archive": false,
    "image": "assets/images/Danfels_Aloe_Vera_Mixed_Vinut__x_3_cases.png"
  },
  {
    "id": 597,
    "sku": "",
    "name": "Nippys Juice Mixed 450ml",
    "description": "",
    "storageLocation": "",
    "category": "Fruit Juice",
    "metro": 0.0,
    "wholesale": 0.0,
    "price": 0.0,
    "cartonQty": 1,
    "weight": 0.0,
    "initialSupplier": "",
    "sellByUnit": true,
    "sellByCarton": false,
    "regional": 0.0,
    "archive": false,
    "image": "assets/images/Nippys_Juice_Mixed_450ml.png"
  },
  {
    "id": 606,
    "sku": "",
    "name": "Nippys Pineapple Juice 450ml",
    "description": "",
    "storageLocation": "",
    "category": "Fruit Juice",
    "metro": 0.0,
    "wholesale": 0.0,
    "price": 0.0,
    "cartonQty": 1,
    "weight": 0.0,
    "initialSupplier": "",
    "sellByUnit": true,
    "sellByCarton": false,
    "regional": 0.0,
    "archive": false,
    "image": "assets/images/Nippys_Pineapple_Juice_450ml.png"
  },
  {
    "id": 615,
    "sku": "RASP600",
    "name": "Schweppes Raspberry 600ml",
    "description": "",
    "storageLocation": "",
    "category": "Soft Drink",
    "metro": 56.0,
    "wholesale": 0.0,
    "price": 50.0,
    "cartonQty": 24,
    "weight": 0.0,
    "initialSupplier": "CJM",
    "sellByUnit": false,
    "sellByCarton": true,
    "regional": 60.0,
    "archive": false,
    "image": "assets/images/Schweppes_Raspberry_600ml.png"
  }
]